{
    "type": "FeatureCollection",
    "features": [
        {
            "type": "Feature",
            "properties": {
                "name": "Hadrians Wall Path"
            },
            "geometry": {
                "type": "LineString",
                "coordinates": [
                    [
                        -1.79326908557015,
                        54.9975535541848
                    ],
                    [
                        -1.79303498987912,
                        54.9974812684867
                    ],
                    [
                        -1.79284637333026,
                        54.9973771859889
                    ],
                    [
                        -1.7932080855265,
                        54.9972569102237
                    ],
                    [
                        -1.79335661111438,
                        54.9972235630606
                    ],
                    [
                        -1.79351723095261,
                        54.9972397135355
                    ],
                    [
                        -1.79341225634749,
                        54.9970685486661
                    ],
                    [
                        -1.79339722534099,
                        54.9969517041956
                    ],
                    [
                        -1.7929311833585,
                        54.9969406587997
                    ],
                    [
                        -1.79261781539007,
                        54.9969510955769
                    ],
                    [
                        -1.79232306010094,
                        54.996975555469
                    ],
                    [
                        -1.79213365782805,
                        54.9970180235578
                    ],
                    [
                        -1.79207704124845,
                        54.9970536538812
                    ],
                    [
                        -1.79092571273687,
                        54.9968577118286
                    ],
                    [
                        -1.79072473317084,
                        54.9968752583516
                    ],
                    [
                        -1.79054892654173,
                        54.996729247244
                    ],
                    [
                        -1.79000819307403,
                        54.9965405441457
                    ],
                    [
                        -1.79005467334437,
                        54.9964787190844
                    ],
                    [
                        -1.79014878507122,
                        54.9964159785312
                    ],
                    [
                        -1.79052494835287,
                        54.9962189315743
                    ],
                    [
                        -1.79105703899167,
                        54.9960940393677
                    ],
                    [
                        -1.79175172127569,
                        54.9959861187521
                    ],
                    [
                        -1.79244244188766,
                        54.9958364381044
                    ],
                    [
                        -1.79258281380828,
                        54.9958132682172
                    ],
                    [
                        -1.79268686508064,
                        54.9958134451608
                    ],
                    [
                        -1.79284025351976,
                        54.995836485553
                    ],
                    [
                        -1.79308960002067,
                        54.9959806861656
                    ],
                    [
                        -1.79330861054614,
                        54.9959451132701
                    ],
                    [
                        -1.79384345131898,
                        54.9952810487788
                    ],
                    [
                        -1.79383555587347,
                        54.9937713738212
                    ],
                    [
                        -1.79418138255462,
                        54.9933855564843
                    ],
                    [
                        -1.79451537466754,
                        54.9928643698163
                    ],
                    [
                        -1.79470072900277,
                        54.9926855174934
                    ],
                    [
                        -1.79508934248301,
                        54.9924999435582
                    ],
                    [
                        -1.79526619105902,
                        54.9924376884847
                    ],
                    [
                        -1.79624651469593,
                        54.9922032840425
                    ],
                    [
                        -1.79686908631553,
                        54.9920851223269
                    ],
                    [
                        -1.79761455076955,
                        54.9920155515174
                    ],
                    [
                        -1.79793500209,
                        54.9919700562272
                    ],
                    [
                        -1.7989893546829,
                        54.991706251026
                    ],
                    [
                        -1.80076266800685,
                        54.9913060365294
                    ],
                    [
                        -1.80082101945255,
                        54.9912978287106
                    ],
                    [
                        -1.80142387061071,
                        54.991319201319
                    ],
                    [
                        -1.80305097716504,
                        54.9912365620987
                    ],
                    [
                        -1.80314456915554,
                        54.9912191004925
                    ],
                    [
                        -1.80343846005769,
                        54.9911213117265
                    ],
                    [
                        -1.80358717508239,
                        54.991042761356
                    ],
                    [
                        -1.80362393020286,
                        54.9904477080986
                    ],
                    [
                        -1.80361758572433,
                        54.9894354512369
                    ],
                    [
                        -1.80353143224146,
                        54.9892489949364
                    ],
                    [
                        -1.80339862752676,
                        54.9890439250663
                    ],
                    [
                        -1.80270813357832,
                        54.988494047451
                    ],
                    [
                        -1.80272299029238,
                        54.9884217694195
                    ],
                    [
                        -1.80279602362423,
                        54.988321773538
                    ],
                    [
                        -1.80288826260241,
                        54.9882505461696
                    ],
                    [
                        -1.80312911360564,
                        54.9881165213371
                    ],
                    [
                        -1.80357022301883,
                        54.9879068144349
                    ],
                    [
                        -1.80352429153768,
                        54.9878689090023
                    ],
                    [
                        -1.80270499925779,
                        54.9879538526376
                    ],
                    [
                        -1.8019608739557,
                        54.988006562936
                    ],
                    [
                        -1.80115445938368,
                        54.9880648283617
                    ],
                    [
                        -1.79992248495746,
                        54.988129757716
                    ],
                    [
                        -1.79982100263258,
                        54.9881166475958
                    ],
                    [
                        -1.79961000895921,
                        54.9880483293531
                    ],
                    [
                        -1.79950063233472,
                        54.9879909063663
                    ],
                    [
                        -1.79935773674635,
                        54.9878842652323
                    ],
                    [
                        -1.79924855198303,
                        54.9877625297837
                    ],
                    [
                        -1.79897377541846,
                        54.9871806680357
                    ],
                    [
                        -1.7985773950185,
                        54.9867590128165
                    ],
                    [
                        -1.79844856088124,
                        54.9865637837568
                    ],
                    [
                        -1.79828358038896,
                        54.9862418789183
                    ],
                    [
                        -1.79790499897855,
                        54.9860185982118
                    ],
                    [
                        -1.79763283310686,
                        54.985893138566
                    ],
                    [
                        -1.79650226508974,
                        54.9861604344462
                    ],
                    [
                        -1.79637739523747,
                        54.986088088316
                    ],
                    [
                        -1.79606342929779,
                        54.9861597012469
                    ],
                    [
                        -1.79462797713262,
                        54.9846963020343
                    ],
                    [
                        -1.79258906570233,
                        54.9847288740302
                    ],
                    [
                        -1.79174180522399,
                        54.9847816006238
                    ],
                    [
                        -1.79121176242456,
                        54.9841854460418
                    ],
                    [
                        -1.79060723074305,
                        54.9842939345225
                    ],
                    [
                        -1.78916697298541,
                        54.9846045073487
                    ],
                    [
                        -1.78883439820982,
                        54.9846564447238
                    ],
                    [
                        -1.78847375996489,
                        54.9846779657853
                    ],
                    [
                        -1.78813002472066,
                        54.984679193095
                    ],
                    [
                        -1.78753674442669,
                        54.9847268670721
                    ],
                    [
                        -1.78592684604446,
                        54.9847870361954
                    ],
                    [
                        -1.78501048440315,
                        54.9848013892703
                    ],
                    [
                        -1.78422639379512,
                        54.9847958398662
                    ],
                    [
                        -1.78383969394988,
                        54.9847721782721
                    ],
                    [
                        -1.78322479201984,
                        54.9847048337352
                    ],
                    [
                        -1.78277295126567,
                        54.9846409218844
                    ],
                    [
                        -1.78222139054994,
                        54.9845337095616
                    ],
                    [
                        -1.7813526440693,
                        54.9842840555243
                    ],
                    [
                        -1.78013877478849,
                        54.9838297016761
                    ],
                    [
                        -1.77986611664966,
                        54.9837005017064
                    ],
                    [
                        -1.77929098487504,
                        54.9835302894528
                    ],
                    [
                        -1.77914273445645,
                        54.9834579146822
                    ],
                    [
                        -1.77904742515816,
                        54.9833757096506
                    ],
                    [
                        -1.77778086298906,
                        54.9829339663468
                    ],
                    [
                        -1.77648118150824,
                        54.9825374462202
                    ],
                    [
                        -1.77560045558131,
                        54.9822813551354
                    ],
                    [
                        -1.77480142835866,
                        54.9820770661322
                    ],
                    [
                        -1.77360027329648,
                        54.9818260113983
                    ],
                    [
                        -1.77267337419888,
                        54.981689889222
                    ],
                    [
                        -1.77146439351942,
                        54.9815713033841
                    ],
                    [
                        -1.76973852994036,
                        54.9814724773053
                    ],
                    [
                        -1.76698848280102,
                        54.9812755433401
                    ],
                    [
                        -1.76656838748195,
                        54.9812659996322
                    ],
                    [
                        -1.765893261794,
                        54.9812581224684
                    ],
                    [
                        -1.76511310475858,
                        54.9812770011125
                    ],
                    [
                        -1.76450239073312,
                        54.9813466331924
                    ],
                    [
                        -1.76365558788005,
                        54.9813865656428
                    ],
                    [
                        -1.76250932843181,
                        54.9815648172261
                    ],
                    [
                        -1.76132217157906,
                        54.9817951881171
                    ],
                    [
                        -1.75708983478991,
                        54.9826916969893
                    ],
                    [
                        -1.75591592178838,
                        54.9829058297074
                    ],
                    [
                        -1.7550713104223,
                        54.9829912061845
                    ],
                    [
                        -1.75467508264985,
                        54.9830453925706
                    ],
                    [
                        -1.75401584669047,
                        54.9830912696503
                    ],
                    [
                        -1.75343756911851,
                        54.9831645896883
                    ],
                    [
                        -1.75332206227531,
                        54.9832136995732
                    ],
                    [
                        -1.75322097840322,
                        54.9832851079239
                    ],
                    [
                        -1.75297799779897,
                        54.98359531214
                    ],
                    [
                        -1.75230788058832,
                        54.9835880248645
                    ],
                    [
                        -1.75228027229948,
                        54.9835703667663
                    ],
                    [
                        -1.75221670937458,
                        54.9834199224483
                    ],
                    [
                        -1.75207967428047,
                        54.9832186362283
                    ],
                    [
                        -1.75198008201855,
                        54.983159690513
                    ],
                    [
                        -1.75183538072961,
                        54.9831265777934
                    ],
                    [
                        -1.75109670058564,
                        54.9831033187747
                    ],
                    [
                        -1.75094491133395,
                        54.9831471646218
                    ],
                    [
                        -1.75085943714505,
                        54.9831972645015
                    ],
                    [
                        -1.75058029507342,
                        54.9832320799465
                    ],
                    [
                        -1.75047391139482,
                        54.9830414842942
                    ],
                    [
                        -1.75037017094228,
                        54.9829904850633
                    ],
                    [
                        -1.7497267762502,
                        54.9829080245606
                    ],
                    [
                        -1.74825112681946,
                        54.9826377168446
                    ],
                    [
                        -1.74680207457961,
                        54.9822975453019
                    ],
                    [
                        -1.74595471790866,
                        54.9820629589413
                    ],
                    [
                        -1.74550155726504,
                        54.9820530273394
                    ],
                    [
                        -1.74442830045624,
                        54.9817442641614
                    ],
                    [
                        -1.74441284678797,
                        54.9817172734167
                    ],
                    [
                        -1.74422597700708,
                        54.981618034128
                    ],
                    [
                        -1.74403893673748,
                        54.981545752528
                    ],
                    [
                        -1.7434929293061,
                        54.9814098128174
                    ],
                    [
                        -1.74303729656684,
                        54.9813233231149
                    ],
                    [
                        -1.74279303628839,
                        54.9812755947914
                    ],
                    [
                        -1.74263226851613,
                        54.9812859371634
                    ],
                    [
                        -1.7424411525754,
                        54.9812464464986
                    ],
                    [
                        -1.74184929031667,
                        54.9810692128235
                    ],
                    [
                        -1.7412334248041,
                        54.9809726062152
                    ],
                    [
                        -1.73786783928443,
                        54.9805417986826
                    ],
                    [
                        -1.73738782522708,
                        54.9804918339853
                    ],
                    [
                        -1.73669602750478,
                        54.9804555675948
                    ],
                    [
                        -1.73512590942562,
                        54.9804418290339
                    ],
                    [
                        -1.73470257770448,
                        54.9804120420275
                    ],
                    [
                        -1.73412993015752,
                        54.9803502014751
                    ],
                    [
                        -1.73343241038651,
                        54.9802376361645
                    ],
                    [
                        -1.73220177959296,
                        54.9799983253012
                    ],
                    [
                        -1.72963425192961,
                        54.9795341047412
                    ],
                    [
                        -1.7258162860024,
                        54.9788173719583
                    ],
                    [
                        -1.72262573162765,
                        54.9782805167342
                    ],
                    [
                        -1.7221386776724,
                        54.9782145236007
                    ],
                    [
                        -1.72157196921271,
                        54.9781646401589
                    ],
                    [
                        -1.72077023185398,
                        54.9781468613709
                    ],
                    [
                        -1.72032509417122,
                        54.9781157710621
                    ],
                    [
                        -1.71874892022393,
                        54.9778787885745
                    ],
                    [
                        -1.71869547805024,
                        54.9778841943626
                    ],
                    [
                        -1.71865792974713,
                        54.9778663420982
                    ],
                    [
                        -1.71835934792541,
                        54.9778190448472
                    ],
                    [
                        -1.71830637257337,
                        54.9777970357758
                    ],
                    [
                        -1.71824471085266,
                        54.9778120500961
                    ],
                    [
                        -1.71819700227771,
                        54.9778054391989
                    ],
                    [
                        -1.71725803367337,
                        54.9773702925728
                    ],
                    [
                        -1.7167941852488,
                        54.9772879780049
                    ],
                    [
                        -1.71510002611479,
                        54.9768308956373
                    ],
                    [
                        -1.71444922907038,
                        54.9767110014348
                    ],
                    [
                        -1.71339074122494,
                        54.9765694260495
                    ],
                    [
                        -1.71290748791172,
                        54.9764712614527
                    ],
                    [
                        -1.71182297361021,
                        54.9762329068489
                    ],
                    [
                        -1.70978048279518,
                        54.9757355269777
                    ],
                    [
                        -1.70872540944386,
                        54.9755151852729
                    ],
                    [
                        -1.70648259693927,
                        54.9751375151048
                    ],
                    [
                        -1.70613295394878,
                        54.9750991021011
                    ],
                    [
                        -1.70472487262476,
                        54.9748828752903
                    ],
                    [
                        -1.70417659763852,
                        54.9748307142294
                    ],
                    [
                        -1.70406381238178,
                        54.9747658300109
                    ],
                    [
                        -1.70396291766343,
                        54.9747557603403
                    ],
                    [
                        -1.702809194022,
                        54.9743301204828
                    ],
                    [
                        -1.70252992297009,
                        54.9743078793507
                    ],
                    [
                        -1.70238758765266,
                        54.9743311571615
                    ],
                    [
                        -1.70221313160992,
                        54.9743187091979
                    ],
                    [
                        -1.70209535074877,
                        54.9743403330293
                    ],
                    [
                        -1.70199612638197,
                        54.9743958600977
                    ],
                    [
                        -1.7019289704864,
                        54.9744082009093
                    ],
                    [
                        -1.70113547891367,
                        54.9744019938472
                    ],
                    [
                        -1.70086661775191,
                        54.9744181784778
                    ],
                    [
                        -1.70061779671347,
                        54.9744486278298
                    ],
                    [
                        -1.70032668970504,
                        54.9745123615438
                    ],
                    [
                        -1.70014567901597,
                        54.9745667495373
                    ],
                    [
                        -1.69997312983778,
                        54.9746430204677
                    ],
                    [
                        -1.69980337792737,
                        54.9747500971238
                    ],
                    [
                        -1.69969884399019,
                        54.9748494058582
                    ],
                    [
                        -1.69954295971716,
                        54.975068948148
                    ],
                    [
                        -1.69946200081025,
                        54.9752437318442
                    ],
                    [
                        -1.69933732611673,
                        54.9756220612418
                    ],
                    [
                        -1.69935828951636,
                        54.9758640062026
                    ],
                    [
                        -1.69942622893188,
                        54.9760664831456
                    ],
                    [
                        -1.69941716381147,
                        54.9761245471405
                    ],
                    [
                        -1.69919158344717,
                        54.9764892406894
                    ],
                    [
                        -1.69881181739548,
                        54.9768294743729
                    ],
                    [
                        -1.69735566734254,
                        54.9769083880141
                    ],
                    [
                        -1.69714727308937,
                        54.9768851055673
                    ],
                    [
                        -1.69698679872527,
                        54.9763484446944
                    ],
                    [
                        -1.6969205252826,
                        54.975918549463
                    ],
                    [
                        -1.69683876670026,
                        54.9757699723843
                    ],
                    [
                        -1.69656372628225,
                        54.9754715572353
                    ],
                    [
                        -1.69529478306781,
                        54.9749266832494
                    ],
                    [
                        -1.69452004396542,
                        54.9746590714554
                    ],
                    [
                        -1.69436139600724,
                        54.9745811186735
                    ],
                    [
                        -1.69427962109751,
                        54.9745138562326
                    ],
                    [
                        -1.69413473597118,
                        54.974272184218
                    ],
                    [
                        -1.69401720096801,
                        54.9735796446486
                    ],
                    [
                        -1.69385002815052,
                        54.9732829507528
                    ],
                    [
                        -1.69369479489749,
                        54.9727533047976
                    ],
                    [
                        -1.69357286525117,
                        54.9727128939066
                    ],
                    [
                        -1.69347096324381,
                        54.9727011343751
                    ],
                    [
                        -1.69279489752452,
                        54.9727479780264
                    ],
                    [
                        -1.69268181554527,
                        54.9727693448996
                    ],
                    [
                        -1.69231416741887,
                        54.9721254683934
                    ],
                    [
                        -1.69222641671054,
                        54.9713434524201
                    ],
                    [
                        -1.69196505764235,
                        54.9707946371041
                    ],
                    [
                        -1.69182626111517,
                        54.9705606463225
                    ],
                    [
                        -1.69154757161476,
                        54.9702364397768
                    ],
                    [
                        -1.69122202611937,
                        54.9699121138027
                    ],
                    [
                        -1.69111316748979,
                        54.9698489347975
                    ],
                    [
                        -1.69041219579186,
                        54.9695955432016
                    ],
                    [
                        -1.68969602844125,
                        54.9692881919593
                    ],
                    [
                        -1.68983847631093,
                        54.9690459288152
                    ],
                    [
                        -1.68983875314387,
                        54.9690099849354
                    ],
                    [
                        -1.68986697025625,
                        54.9688887734608
                    ],
                    [
                        -1.68823479507026,
                        54.9688149390794
                    ],
                    [
                        -1.68754925890244,
                        54.9687614915096
                    ],
                    [
                        -1.68742271356419,
                        54.9687648826107
                    ],
                    [
                        -1.68736935072838,
                        54.9687471975124
                    ],
                    [
                        -1.68708357209391,
                        54.9687153815096
                    ],
                    [
                        -1.68682105009226,
                        54.9685950409856
                    ],
                    [
                        -1.68660486152701,
                        54.9686633628705
                    ],
                    [
                        -1.68636871989364,
                        54.9687123451297
                    ],
                    [
                        -1.68623249008077,
                        54.9686953034132
                    ],
                    [
                        -1.68584550196508,
                        54.9686093625722
                    ],
                    [
                        -1.68533808723278,
                        54.9685188491233
                    ],
                    [
                        -1.68335195320004,
                        54.9682331446345
                    ],
                    [
                        -1.68321317656303,
                        54.9681883742335
                    ],
                    [
                        -1.68311293574962,
                        54.9681900598862
                    ],
                    [
                        -1.68283329999358,
                        54.9681143947592
                    ],
                    [
                        -1.68241008360804,
                        54.9680292670054
                    ],
                    [
                        -1.68110926138078,
                        54.9678710288176
                    ],
                    [
                        -1.68003847972064,
                        54.9676681197676
                    ],
                    [
                        -1.67937349592273,
                        54.9675595994374
                    ],
                    [
                        -1.67595996469681,
                        54.9670658544993
                    ],
                    [
                        -1.67514615226565,
                        54.9669839228564
                    ],
                    [
                        -1.6747572154954,
                        54.9669239375033
                    ],
                    [
                        -1.67466371912458,
                        54.9668944468526
                    ],
                    [
                        -1.67440335052671,
                        54.9669001914713
                    ],
                    [
                        -1.67426545722238,
                        54.9668489997738
                    ],
                    [
                        -1.67384107605841,
                        54.9667736662853
                    ],
                    [
                        -1.67079068105366,
                        54.9663323194743
                    ],
                    [
                        -1.6701938042111,
                        54.9662630694482
                    ],
                    [
                        -1.66971065099631,
                        54.9662729263528
                    ],
                    [
                        -1.66951569304135,
                        54.9662619915246
                    ],
                    [
                        -1.66878684728794,
                        54.9661850410215
                    ],
                    [
                        -1.66717598537998,
                        54.9660703113168
                    ],
                    [
                        -1.66676684959528,
                        54.9659958978739
                    ],
                    [
                        -1.66678798358776,
                        54.9658999970079
                    ],
                    [
                        -1.66623172729592,
                        54.9658473596945
                    ],
                    [
                        -1.66379173357425,
                        54.9655117549863
                    ],
                    [
                        -1.66124227147832,
                        54.9651973635949
                    ],
                    [
                        -1.65989097308394,
                        54.9650462243415
                    ],
                    [
                        -1.65807758580469,
                        54.9648704095619
                    ],
                    [
                        -1.65717582069761,
                        54.9647546487911
                    ],
                    [
                        -1.65699558435674,
                        54.9646445101025
                    ],
                    [
                        -1.65679339189588,
                        54.9645450926658
                    ],
                    [
                        -1.65660712486431,
                        54.9644097751408
                    ],
                    [
                        -1.65645378112742,
                        54.964076854594
                    ],
                    [
                        -1.65634545297998,
                        54.9639597288194
                    ],
                    [
                        -1.65617473118785,
                        54.9638334406427
                    ],
                    [
                        -1.65608140837869,
                        54.9637882463082
                    ],
                    [
                        -1.65586329768281,
                        54.9637247270067
                    ],
                    [
                        -1.65017107664204,
                        54.9625642054726
                    ],
                    [
                        -1.6501790402056,
                        54.9623877804312
                    ],
                    [
                        -1.64925524288098,
                        54.9621201740908
                    ],
                    [
                        -1.64868480690177,
                        54.9619780633549
                    ],
                    [
                        -1.64851885259124,
                        54.9619570214243
                    ],
                    [
                        -1.6485044293993,
                        54.9618282232506
                    ],
                    [
                        -1.64708585176908,
                        54.9615176649964
                    ],
                    [
                        -1.64494061216107,
                        54.9611833231807
                    ],
                    [
                        -1.64484119136039,
                        54.9611428533819
                    ],
                    [
                        -1.64478793709307,
                        54.9610980502524
                    ],
                    [
                        -1.64473793451134,
                        54.9610905986266
                    ],
                    [
                        -1.64463835897226,
                        54.9611323319209
                    ],
                    [
                        -1.64458792069342,
                        54.9611314253888
                    ],
                    [
                        -1.64350498621154,
                        54.960984213318
                    ],
                    [
                        -1.64336373292467,
                        54.9609895589494
                    ],
                    [
                        -1.64325491482637,
                        54.9609514991746
                    ],
                    [
                        -1.64218395825062,
                        54.960811386125
                    ],
                    [
                        -1.64149466178497,
                        54.9606982186276
                    ],
                    [
                        -1.64071791129978,
                        54.9606038210356
                    ],
                    [
                        -1.63940703181221,
                        54.9605063848902
                    ],
                    [
                        -1.63935179567769,
                        54.9604998626914
                    ],
                    [
                        -1.63924405367999,
                        54.9604503289549
                    ],
                    [
                        -1.63894900805465,
                        54.9604263168893
                    ],
                    [
                        -1.63782936813191,
                        54.9603694478415
                    ],
                    [
                        -1.63764275702814,
                        54.9603900982518
                    ],
                    [
                        -1.63753645033322,
                        54.9603566102898
                    ],
                    [
                        -1.63648513508392,
                        54.9603187106329
                    ],
                    [
                        -1.63628280855293,
                        54.9603511010066
                    ],
                    [
                        -1.63601949143481,
                        54.960322704177
                    ],
                    [
                        -1.63568049970182,
                        54.9603130529045
                    ],
                    [
                        -1.63561637876265,
                        54.960327563328
                    ],
                    [
                        -1.63545308327287,
                        54.9603301873792
                    ],
                    [
                        -1.63536531227304,
                        54.9603127708671
                    ],
                    [
                        -1.63534992322145,
                        54.960275194913
                    ],
                    [
                        -1.63525463176419,
                        54.9602672200414
                    ],
                    [
                        -1.63517441033497,
                        54.9602349502868
                    ],
                    [
                        -1.63510919589225,
                        54.9602301818165
                    ],
                    [
                        -1.63443535722496,
                        54.9602739120456
                    ],
                    [
                        -1.63412238283312,
                        54.9602645349255
                    ],
                    [
                        -1.6340510064668,
                        54.9602700401407
                    ],
                    [
                        -1.63395421098438,
                        54.9603045580601
                    ],
                    [
                        -1.63318169675562,
                        54.9602951243847
                    ],
                    [
                        -1.63105290322883,
                        54.9603118394593
                    ],
                    [
                        -1.62923566101438,
                        54.9603534746915
                    ],
                    [
                        -1.6282488865497,
                        54.9604122011144
                    ],
                    [
                        -1.62811153669522,
                        54.960444009741
                    ],
                    [
                        -1.62800077714562,
                        54.9604355982319
                    ],
                    [
                        -1.62765232596886,
                        54.9604715275021
                    ],
                    [
                        -1.62669663987358,
                        54.9605964297528
                    ],
                    [
                        -1.62612625508632,
                        54.9606984216028
                    ],
                    [
                        -1.62606069226402,
                        54.9607182603577
                    ],
                    [
                        -1.62602575701914,
                        54.960750240918
                    ],
                    [
                        -1.6259077242387,
                        54.9607335908984
                    ],
                    [
                        -1.62544340781598,
                        54.9607849968645
                    ],
                    [
                        -1.62506387723667,
                        54.9608503948404
                    ],
                    [
                        -1.62453164777535,
                        54.9609679906728
                    ],
                    [
                        -1.62418543004825,
                        54.9610738725213
                    ],
                    [
                        -1.62394106231598,
                        54.9611236949781
                    ],
                    [
                        -1.62328031972071,
                        54.961328530587
                    ],
                    [
                        -1.62283061510302,
                        54.9614753708794
                    ],
                    [
                        -1.62255998270757,
                        54.9615750427125
                    ],
                    [
                        -1.62250400296852,
                        54.9616010045826
                    ],
                    [
                        -1.62248075683728,
                        54.9616328127831
                    ],
                    [
                        -1.62235502263741,
                        54.9616525797934
                    ],
                    [
                        -1.62221591003749,
                        54.9617325116734
                    ],
                    [
                        -1.62205646356661,
                        54.9617669542448
                    ],
                    [
                        -1.62154798953611,
                        54.9619629531811
                    ],
                    [
                        -1.62146006675124,
                        54.9620548403427
                    ],
                    [
                        -1.62138758611937,
                        54.9620495315141
                    ],
                    [
                        -1.62130469906689,
                        54.9620633829608
                    ],
                    [
                        -1.62118151148924,
                        54.9621123995053
                    ],
                    [
                        -1.62089900086019,
                        54.9622499622534
                    ],
                    [
                        -1.62084158394176,
                        54.9622926718187
                    ],
                    [
                        -1.62056246175629,
                        54.9624142875771
                    ],
                    [
                        -1.62052271382705,
                        54.9624576783858
                    ],
                    [
                        -1.62051228576489,
                        54.9625361051164
                    ],
                    [
                        -1.62045891399795,
                        54.9625414167445
                    ],
                    [
                        -1.6203696509028,
                        54.9625234096478
                    ],
                    [
                        -1.62031072700108,
                        54.9625394972008
                    ],
                    [
                        -1.6200930352222,
                        54.9626438900004
                    ],
                    [
                        -1.62005184980165,
                        54.9626996905763
                    ],
                    [
                        -1.61999085130616,
                        54.9626984155946
                    ],
                    [
                        -1.61974578016751,
                        54.9628105600691
                    ],
                    [
                        -1.61967802681611,
                        54.9628567575899
                    ],
                    [
                        -1.61862646783368,
                        54.9633429943198
                    ],
                    [
                        -1.61728892136185,
                        54.9639919779235
                    ],
                    [
                        -1.61748517264882,
                        54.9641028936237
                    ],
                    [
                        -1.61732151759386,
                        54.9641999702048
                    ],
                    [
                        -1.61713025215072,
                        54.9640932709576
                    ],
                    [
                        -1.61683002995791,
                        54.9642149861383
                    ],
                    [
                        -1.61646721547072,
                        54.9643937786484
                    ],
                    [
                        -1.61587028676487,
                        54.9646916426707
                    ],
                    [
                        -1.61579772293984,
                        54.9647471891455
                    ],
                    [
                        -1.61553183690968,
                        54.9648689124051
                    ],
                    [
                        -1.61544207076726,
                        54.9649305958279
                    ],
                    [
                        -1.61533092264683,
                        54.9649247281431
                    ],
                    [
                        -1.61527734267012,
                        54.9649422760176
                    ],
                    [
                        -1.61483486538043,
                        54.9651358215523
                    ],
                    [
                        -1.61362143558557,
                        54.9656283252044
                    ],
                    [
                        -1.61211621053755,
                        54.9663213235534
                    ],
                    [
                        -1.6116612345901,
                        54.9665131912365
                    ],
                    [
                        -1.61119482806866,
                        54.9667696870436
                    ],
                    [
                        -1.60950552254504,
                        54.9674651717163
                    ],
                    [
                        -1.60966632052199,
                        54.9675912492969
                    ],
                    [
                        -1.60934513891191,
                        54.9677180207143
                    ],
                    [
                        -1.60921770400318,
                        54.9676626972999
                    ],
                    [
                        -1.60866419318111,
                        54.9678987864867
                    ],
                    [
                        -1.60795429744644,
                        54.9681312560575
                    ],
                    [
                        -1.60716400908521,
                        54.9683508878111
                    ],
                    [
                        -1.60668263329671,
                        54.968412814061
                    ],
                    [
                        -1.60612195560108,
                        54.9685243578934
                    ],
                    [
                        -1.60382116673965,
                        54.9691838479697
                    ],
                    [
                        -1.60312250966555,
                        54.9694371729682
                    ],
                    [
                        -1.60266193937898,
                        54.96957226086
                    ],
                    [
                        -1.60262883172923,
                        54.9696031551296
                    ],
                    [
                        -1.60043298683448,
                        54.9701944489581
                    ],
                    [
                        -1.60029149607412,
                        54.9702856435882
                    ],
                    [
                        -1.60018099519123,
                        54.9704021010984
                    ],
                    [
                        -1.60003978875002,
                        54.9704645406088
                    ],
                    [
                        -1.59867724848456,
                        54.9708195046878
                    ],
                    [
                        -1.59767575098066,
                        54.9709959234221
                    ],
                    [
                        -1.59708136622253,
                        54.9710748337371
                    ],
                    [
                        -1.59476749776081,
                        54.9712702790744
                    ],
                    [
                        -1.59441404540285,
                        54.9712518192179
                    ],
                    [
                        -1.59360212838536,
                        54.971258180173
                    ],
                    [
                        -1.59212062463667,
                        54.971226021106
                    ],
                    [
                        -1.59111281275789,
                        54.9711183538829
                    ],
                    [
                        -1.58990081963847,
                        54.9709374418061
                    ],
                    [
                        -1.58875809359068,
                        54.9706831457891
                    ],
                    [
                        -1.58862666472361,
                        54.9706701571418
                    ],
                    [
                        -1.58853954901338,
                        54.9707106717384
                    ],
                    [
                        -1.58882444264795,
                        54.9711616681914
                    ],
                    [
                        -1.5885393174777,
                        54.971338670943
                    ],
                    [
                        -1.58826915035432,
                        54.9712700109407
                    ],
                    [
                        -1.58812865781449,
                        54.9712605496394
                    ],
                    [
                        -1.58758424162001,
                        54.9710340525103
                    ],
                    [
                        -1.58735113276352,
                        54.9709164424417
                    ],
                    [
                        -1.58500635145686,
                        54.9695605466167
                    ],
                    [
                        -1.58446318133543,
                        54.969217219251
                    ],
                    [
                        -1.58367131533475,
                        54.9687562189543
                    ],
                    [
                        -1.58298880278467,
                        54.9682955879975
                    ],
                    [
                        -1.58278677559236,
                        54.9681960478899
                    ],
                    [
                        -1.58252227239121,
                        54.9680962932509
                    ],
                    [
                        -1.581868036631,
                        54.9679233108146
                    ],
                    [
                        -1.58133885285393,
                        54.9677417687005
                    ],
                    [
                        -1.58076375222566,
                        54.9674702043109
                    ],
                    [
                        -1.58056154750199,
                        54.9673886322393
                    ],
                    [
                        -1.58029677418221,
                        54.9673158303594
                    ],
                    [
                        -1.58003172068957,
                        54.967269985497
                    ],
                    [
                        -1.57744227980315,
                        54.9669465099057
                    ],
                    [
                        -1.57749073889876,
                        54.9667939128544
                    ],
                    [
                        -1.57757656165582,
                        54.9660573430634
                    ],
                    [
                        -1.57737446480283,
                        54.9659667798328
                    ],
                    [
                        -1.57726532454746,
                        54.9659484285685
                    ],
                    [
                        -1.57629755062023,
                        54.9658911474866
                    ],
                    [
                        -1.57495493889421,
                        54.9658325507273
                    ],
                    [
                        -1.57475180536453,
                        54.9658408276157
                    ],
                    [
                        -1.57440763167965,
                        54.965893542205
                    ],
                    [
                        -1.57434610791138,
                        54.965803465214
                    ],
                    [
                        -1.57413277233076,
                        54.965299492422
                    ],
                    [
                        -1.57402339702653,
                        54.9652649847362
                    ],
                    [
                        -1.57241397119739,
                        54.9654271109972
                    ],
                    [
                        -1.57244429000113,
                        54.9655405738066
                    ],
                    [
                        -1.57215241628191,
                        54.9655667542045
                    ],
                    [
                        -1.57212229096875,
                        54.9654351551668
                    ],
                    [
                        -1.5715465217053,
                        54.9654784729249
                    ],
                    [
                        -1.57147520181053,
                        54.9655238088894
                    ],
                    [
                        -1.57135044725414,
                        54.9655053973518
                    ],
                    [
                        -1.57002318631723,
                        54.9654737587376
                    ],
                    [
                        -1.56994490336699,
                        54.965491454642
                    ],
                    [
                        -1.56988204662908,
                        54.9655271773821
                    ],
                    [
                        -1.5698663324272,
                        54.9655361080619
                    ],
                    [
                        -1.5696269857408,
                        54.9653954307774
                    ],
                    [
                        -1.56897584385254,
                        54.9653156223435
                    ],
                    [
                        -1.56752346447108,
                        54.9650841582688
                    ],
                    [
                        -1.5673026463938,
                        54.9652856493758
                    ],
                    [
                        -1.56602032769142,
                        54.9650560134872
                    ],
                    [
                        -1.56585725636225,
                        54.9650440124559
                    ],
                    [
                        -1.56582016975518,
                        54.9650631511054
                    ],
                    [
                        -1.56231304609616,
                        54.9639232157326
                    ],
                    [
                        -1.56142855272225,
                        54.9636586286745
                    ],
                    [
                        -1.56042484122405,
                        54.9632778795607
                    ],
                    [
                        -1.55971456002297,
                        54.9629301601284
                    ],
                    [
                        -1.55912629599258,
                        54.9627068916229
                    ],
                    [
                        -1.55874512714477,
                        54.962526220675
                    ],
                    [
                        -1.55842265080056,
                        54.9623224952357
                    ],
                    [
                        -1.55789477717994,
                        54.9620974915371
                    ],
                    [
                        -1.55681096003336,
                        54.9617658392768
                    ],
                    [
                        -1.55600111541172,
                        54.9615844808195
                    ],
                    [
                        -1.55618248965302,
                        54.9614432041334
                    ],
                    [
                        -1.55627668429469,
                        54.961398616455
                    ],
                    [
                        -1.55644866476955,
                        54.9613812707485
                    ],
                    [
                        -1.55716544730676,
                        54.961527659419
                    ],
                    [
                        -1.55730619467328,
                        54.9615101988872
                    ],
                    [
                        -1.55733772422298,
                        54.9614833549163
                    ],
                    [
                        -1.55733821799638,
                        54.9614384256826
                    ],
                    [
                        -1.55729166444731,
                        54.9614112977859
                    ],
                    [
                        -1.55694879106068,
                        54.9613471470297
                    ],
                    [
                        -1.55679321853394,
                        54.9612926635272
                    ],
                    [
                        -1.55662262337433,
                        54.961184207875
                    ],
                    [
                        -1.55651548438961,
                        54.960986121087
                    ],
                    [
                        -1.55525759753081,
                        54.960343511567
                    ],
                    [
                        -1.55483764878704,
                        54.9601892111407
                    ],
                    [
                        -1.5541835617689,
                        54.9600250658469
                    ],
                    [
                        -1.55405863329442,
                        54.9600246082898
                    ],
                    [
                        -1.55393108947389,
                        54.9601025178412
                    ],
                    [
                        -1.55383903973824,
                        54.9600861706954
                    ],
                    [
                        -1.55371402845438,
                        54.9600924656176
                    ],
                    [
                        -1.55281459885029,
                        54.9600495871119
                    ],
                    [
                        -1.55182103790099,
                        54.9600730043702
                    ],
                    [
                        -1.55159241626843,
                        54.9600607284392
                    ],
                    [
                        -1.55130660451702,
                        54.9601806863661
                    ],
                    [
                        -1.55063643786496,
                        54.9602737927289
                    ],
                    [
                        -1.550464925733,
                        54.9603166770452
                    ],
                    [
                        -1.55035386902772,
                        54.9603711780442
                    ],
                    [
                        -1.5502221368488,
                        54.9603837241195
                    ],
                    [
                        -1.55005867279531,
                        54.9604561015849
                    ],
                    [
                        -1.5500544789863,
                        54.9604740576071
                    ],
                    [
                        -1.55011422641252,
                        54.9605176458684
                    ],
                    [
                        -1.54999150186671,
                        54.960645062459
                    ],
                    [
                        -1.54939370564174,
                        54.9606386618775
                    ],
                    [
                        -1.54912244263967,
                        54.9607294858117
                    ],
                    [
                        -1.54918708310126,
                        54.9607923923336
                    ],
                    [
                        -1.54881688967101,
                        54.960930874203
                    ],
                    [
                        -1.5482056327783,
                        54.9611263039025
                    ],
                    [
                        -1.54779758685432,
                        54.9613045131084
                    ],
                    [
                        -1.54780714000683,
                        54.9613171616377
                    ],
                    [
                        -1.54771223910107,
                        54.9613622128255
                    ],
                    [
                        -1.54713424054158,
                        54.9615850769864
                    ],
                    [
                        -1.5469288423808,
                        54.9616368110846
                    ],
                    [
                        -1.54637924805901,
                        54.9618211438554
                    ],
                    [
                        -1.54571086879237,
                        54.962070528734
                    ],
                    [
                        -1.54546360457256,
                        54.9623274057719
                    ],
                    [
                        -1.54546280843707,
                        54.9623614174
                    ],
                    [
                        -1.54515142772546,
                        54.9625037264458
                    ],
                    [
                        -1.54466316614504,
                        54.9628626678847
                    ],
                    [
                        -1.54460895417585,
                        54.9629359669091
                    ],
                    [
                        -1.54453222252149,
                        54.9632320378412
                    ],
                    [
                        -1.54448407573821,
                        54.9636009949698
                    ],
                    [
                        -1.54441450630578,
                        54.9637608985296
                    ],
                    [
                        -1.54428182701544,
                        54.9639139717465
                    ],
                    [
                        -1.54392762035965,
                        54.9641948958345
                    ],
                    [
                        -1.54369193923012,
                        54.9644459832655
                    ],
                    [
                        -1.54339698109362,
                        54.9649451952345
                    ],
                    [
                        -1.54320822800869,
                        54.9650961734395
                    ],
                    [
                        -1.54306047425527,
                        54.9651869925168
                    ],
                    [
                        -1.54302067015116,
                        54.9652395588981
                    ],
                    [
                        -1.54288816421027,
                        54.9652921088287
                    ],
                    [
                        -1.54225305751964,
                        54.9656472028354
                    ],
                    [
                        -1.54163515041794,
                        54.9660400140795
                    ],
                    [
                        -1.54135767455056,
                        54.9661880466463
                    ],
                    [
                        -1.54122130857542,
                        54.9663114723971
                    ],
                    [
                        -1.54125246846267,
                        54.9664192679179
                    ],
                    [
                        -1.54116167262514,
                        54.96655621341
                    ],
                    [
                        -1.54093076172451,
                        54.9666219172374
                    ],
                    [
                        -1.54044283793448,
                        54.9670941158395
                    ],
                    [
                        -1.54031544041365,
                        54.9672590547399
                    ],
                    [
                        -1.5403557449427,
                        54.9674492696255
                    ],
                    [
                        -1.54018628500117,
                        54.9676586966311
                    ],
                    [
                        -1.53991470846231,
                        54.9682044964168
                    ],
                    [
                        -1.5397994679419,
                        54.9686015565746
                    ],
                    [
                        -1.53974233634475,
                        54.9689737926398
                    ],
                    [
                        -1.53969777774627,
                        54.9695332542752
                    ],
                    [
                        -1.53962601800271,
                        54.9697443060548
                    ],
                    [
                        -1.53965979307611,
                        54.9698516553144
                    ],
                    [
                        -1.53990272063361,
                        54.9700913917391
                    ],
                    [
                        -1.53992194770374,
                        54.970137491714
                    ],
                    [
                        -1.53963013195465,
                        54.9702945251064
                    ],
                    [
                        -1.53932701940697,
                        54.9705910195201
                    ],
                    [
                        -1.53923345119585,
                        54.9707912365327
                    ],
                    [
                        -1.53913520309159,
                        54.9713445520414
                    ],
                    [
                        -1.53914656786028,
                        54.971407976516
                    ],
                    [
                        -1.53927580330481,
                        54.9716645902472
                    ],
                    [
                        -1.53927560146815,
                        54.972062965612
                    ],
                    [
                        -1.53930251732539,
                        54.9722423340122
                    ],
                    [
                        -1.53934234078584,
                        54.9723223665918
                    ],
                    [
                        -1.53954638763914,
                        54.9725344299755
                    ],
                    [
                        -1.53959338293153,
                        54.9726851588371
                    ],
                    [
                        -1.53959074021597,
                        54.9730930224086
                    ],
                    [
                        -1.53953928489675,
                        54.9736551165484
                    ],
                    [
                        -1.53958154942388,
                        54.9737487552701
                    ],
                    [
                        -1.53955259365729,
                        54.973788533695
                    ],
                    [
                        -1.53950261998423,
                        54.974128640213
                    ],
                    [
                        -1.53928529331722,
                        54.9749627613002
                    ],
                    [
                        -1.53900309556115,
                        54.9756946250564
                    ],
                    [
                        -1.53896561793302,
                        54.9760821924129
                    ],
                    [
                        -1.53893734142051,
                        54.9761672232202
                    ],
                    [
                        -1.53878846143517,
                        54.9763055769163
                    ],
                    [
                        -1.53868566730439,
                        54.9766103576658
                    ],
                    [
                        -1.53866197810839,
                        54.9767975158701
                    ],
                    [
                        -1.53872499048738,
                        54.9770971214478
                    ],
                    [
                        -1.53880793437734,
                        54.977280427716
                    ],
                    [
                        -1.53884457170873,
                        54.9773230729541
                    ],
                    [
                        -1.53897239697405,
                        54.9773876680727
                    ],
                    [
                        -1.53895518235656,
                        54.9780107097529
                    ],
                    [
                        -1.53887128054662,
                        54.9782864351769
                    ],
                    [
                        -1.53887018603655,
                        54.9784670794774
                    ],
                    [
                        -1.53920944345368,
                        54.9792710100464
                    ],
                    [
                        -1.53924991329034,
                        54.9792932485371
                    ],
                    [
                        -1.539404188648,
                        54.979537868268
                    ],
                    [
                        -1.53949677954551,
                        54.9797801454677
                    ],
                    [
                        -1.53950604919151,
                        54.979940638756
                    ],
                    [
                        -1.53936435604497,
                        54.980392802586
                    ],
                    [
                        -1.53923917744214,
                        54.9809210563264
                    ],
                    [
                        -1.53908181861042,
                        54.981344414585
                    ],
                    [
                        -1.5389923470055,
                        54.9815194223918
                    ],
                    [
                        -1.53866339195464,
                        54.9821090774201
                    ],
                    [
                        -1.53849560749951,
                        54.9823378921373
                    ],
                    [
                        -1.53835770395046,
                        54.9826733079574
                    ],
                    [
                        -1.53827854879177,
                        54.9827191680715
                    ],
                    [
                        -1.53791919364423,
                        54.9831331400157
                    ],
                    [
                        -1.53773180029278,
                        54.9832039623849
                    ],
                    [
                        -1.53726105742788,
                        54.9834277878262
                    ],
                    [
                        -1.53677163672167,
                        54.9836984204075
                    ],
                    [
                        -1.53612154970921,
                        54.9839709048998
                    ],
                    [
                        -1.5340497296935,
                        54.9853205445182
                    ],
                    [
                        -1.5335532135314,
                        54.9856560199193
                    ],
                    [
                        -1.53353192601899,
                        54.9857084023911
                    ],
                    [
                        -1.53346506277318,
                        54.9857354813094
                    ],
                    [
                        -1.53282509329706,
                        54.9861681476407
                    ],
                    [
                        -1.53253857819035,
                        54.9863041412852
                    ],
                    [
                        -1.53215087294451,
                        54.9865298310856
                    ],
                    [
                        -1.53138760335599,
                        54.9870251610684
                    ],
                    [
                        -1.5309044962022,
                        54.987435269718
                    ],
                    [
                        -1.53055062795585,
                        54.987662407519
                    ],
                    [
                        -1.53013966338608,
                        54.9880710460886
                    ],
                    [
                        -1.52988840787917,
                        54.9882528058341
                    ],
                    [
                        -1.52991349624567,
                        54.9882700860504
                    ],
                    [
                        -1.53010352439729,
                        54.9882056858315
                    ],
                    [
                        -1.53019913410817,
                        54.9882091846
                    ],
                    [
                        -1.53028128434991,
                        54.9882448944513
                    ],
                    [
                        -1.53100491592444,
                        54.9887060619457
                    ]
                ]
            }
        }
    ]
}