{
    "type": "FeatureCollection",
    "features": [
        {
            "type": "Feature",
            "properties": {
                "name": "Pennine Way"
            },
            "geometry": {
                "type": "LineString",
                "coordinates": [
                    [
                        -1.81682450525045,
                        53.37046268101
                    ],
                    [
                        -1.81729380782722,
                        53.370362871941
                    ],
                    [
                        -1.81818756190213,
                        53.370376723991
                    ],
                    [
                        -1.81904411834136,
                        53.3702980869628
                    ],
                    [
                        -1.81946842435865,
                        53.3702757378106
                    ],
                    [
                        -1.8211364368353,
                        53.370212756569
                    ],
                    [
                        -1.8216235935845,
                        53.3702075864107
                    ],
                    [
                        -1.82186064139271,
                        53.3702200427159
                    ],
                    [
                        -1.82194582474609,
                        53.3701798466704
                    ],
                    [
                        -1.82216762288986,
                        53.3701253424997
                    ],
                    [
                        -1.82265264758876,
                        53.3700252193376
                    ],
                    [
                        -1.82357942406739,
                        53.3698760250451
                    ],
                    [
                        -1.8238791114154,
                        53.3697985291245
                    ],
                    [
                        -1.82414551075052,
                        53.3698008013647
                    ],
                    [
                        -1.8242783727415,
                        53.3697502784069
                    ],
                    [
                        -1.8243581498892,
                        53.3696647414122
                    ],
                    [
                        -1.8251101847906,
                        53.369273296598
                    ],
                    [
                        -1.82567266457134,
                        53.3690764177248
                    ],
                    [
                        -1.82680278050961,
                        53.3687585538026
                    ],
                    [
                        -1.8271749230176,
                        53.3686969213548
                    ],
                    [
                        -1.82739985067211,
                        53.3686859877988
                    ],
                    [
                        -1.82749983159694,
                        53.3686075347832
                    ],
                    [
                        -1.82758758500946,
                        53.3685793426831
                    ],
                    [
                        -1.82782665854618,
                        53.3684415169012
                    ],
                    [
                        -1.82817849385038,
                        53.3682802656324
                    ],
                    [
                        -1.82844300626928,
                        53.3681958116792
                    ],
                    [
                        -1.82868942918329,
                        53.3680465225527
                    ],
                    [
                        -1.82918574614711,
                        53.3679107294368
                    ],
                    [
                        -1.82969296060579,
                        53.3678004432292
                    ],
                    [
                        -1.82989088688107,
                        53.3677722686633
                    ],
                    [
                        -1.8300138835894,
                        53.3677012294859
                    ],
                    [
                        -1.83025014773109,
                        53.3676227879098
                    ],
                    [
                        -1.8308124790339,
                        53.3674530723957
                    ],
                    [
                        -1.83137301782928,
                        53.3673091813418
                    ],
                    [
                        -1.83175469826167,
                        53.3671583910413
                    ],
                    [
                        -1.83241742314344,
                        53.3669994264065
                    ],
                    [
                        -1.83271749640731,
                        53.3669069814564
                    ],
                    [
                        -1.83328760283454,
                        53.3667948524027
                    ],
                    [
                        -1.83376827549489,
                        53.3667887922299
                    ],
                    [
                        -1.83394495542568,
                        53.3667354331227
                    ],
                    [
                        -1.8341353052834,
                        53.3667310311314
                    ],
                    [
                        -1.83438328427049,
                        53.3666859605917
                    ],
                    [
                        -1.834743191796,
                        53.3667763899941
                    ],
                    [
                        -1.83514592100478,
                        53.3667812887671
                    ],
                    [
                        -1.83618526583827,
                        53.36662587848
                    ],
                    [
                        -1.83643919029786,
                        53.3665658332074
                    ],
                    [
                        -1.8366241649298,
                        53.3665815417795
                    ],
                    [
                        -1.83692822063633,
                        53.3665599910574
                    ],
                    [
                        -1.83730639568057,
                        53.3665971909598
                    ],
                    [
                        -1.83761237060648,
                        53.3665581313135
                    ],
                    [
                        -1.83784601185887,
                        53.3665822400472
                    ],
                    [
                        -1.83819312585487,
                        53.3666704547845
                    ],
                    [
                        -1.83834406567528,
                        53.3666926556715
                    ],
                    [
                        -1.8385180435681,
                        53.3666671184466
                    ],
                    [
                        -1.83938431746589,
                        53.3664265592221
                    ],
                    [
                        -1.83973371702891,
                        53.3663072788281
                    ],
                    [
                        -1.84064449657401,
                        53.3660602631983
                    ],
                    [
                        -1.84110236239669,
                        53.365865477816
                    ],
                    [
                        -1.84147928551188,
                        53.3657642285187
                    ],
                    [
                        -1.84163753059579,
                        53.3656987160742
                    ],
                    [
                        -1.84204331872513,
                        53.3655955095153
                    ],
                    [
                        -1.84300194966023,
                        53.3650589604782
                    ],
                    [
                        -1.84327789427117,
                        53.3649763987115
                    ],
                    [
                        -1.84446577536459,
                        53.3649449080487
                    ],
                    [
                        -1.845389637859,
                        53.364956076146
                    ],
                    [
                        -1.84609830780739,
                        53.3648952504168
                    ],
                    [
                        -1.84646674092611,
                        53.3648329661008
                    ],
                    [
                        -1.84651996944895,
                        53.3647152836995
                    ],
                    [
                        -1.84655607217305,
                        53.3646923551267
                    ],
                    [
                        -1.84687533538785,
                        53.3646942021893
                    ],
                    [
                        -1.84697146727803,
                        53.3646641683839
                    ],
                    [
                        -1.84726979719872,
                        53.3643463260013
                    ],
                    [
                        -1.84734687921499,
                        53.3643736418244
                    ],
                    [
                        -1.84741380918027,
                        53.364470795076
                    ],
                    [
                        -1.84743327890238,
                        53.3645607868047
                    ],
                    [
                        -1.84753978073613,
                        53.3646650914129
                    ],
                    [
                        -1.84761099098777,
                        53.3646746560857
                    ],
                    [
                        -1.84776939543043,
                        53.3646488176876
                    ],
                    [
                        -1.84794378811594,
                        53.3645851124393
                    ],
                    [
                        -1.84808225825082,
                        53.3645994902655
                    ],
                    [
                        -1.84829537675225,
                        53.3647725933965
                    ],
                    [
                        -1.84865036582013,
                        53.3651210634394
                    ],
                    [
                        -1.84884769882756,
                        53.3652846716197
                    ],
                    [
                        -1.84895038086944,
                        53.3653487191802
                    ],
                    [
                        -1.84945228064488,
                        53.365571900251
                    ],
                    [
                        -1.84964206723142,
                        53.3656265917444
                    ],
                    [
                        -1.85076992727027,
                        53.3656848201604
                    ],
                    [
                        -1.85101917933102,
                        53.3657182806063
                    ],
                    [
                        -1.85130316883297,
                        53.3658315035717
                    ],
                    [
                        -1.85174613421675,
                        53.365941543153
                    ],
                    [
                        -1.85209793504958,
                        53.3659454030184
                    ],
                    [
                        -1.85272735947387,
                        53.3658965620236
                    ],
                    [
                        -1.85296763919907,
                        53.3658917249191
                    ],
                    [
                        -1.85373114784619,
                        53.3659457020377
                    ],
                    [
                        -1.85437436734389,
                        53.3660508439003
                    ],
                    [
                        -1.85503481206871,
                        53.3661337653642
                    ],
                    [
                        -1.85538918654706,
                        53.3662214463072
                    ],
                    [
                        -1.85562633524015,
                        53.3662987198945
                    ],
                    [
                        -1.8561636431374,
                        53.3664276789338
                    ],
                    [
                        -1.85616798256098,
                        53.3664510967466
                    ],
                    [
                        -1.85669863205002,
                        53.3665495857142
                    ],
                    [
                        -1.85679031744818,
                        53.366585503306
                    ],
                    [
                        -1.85705567998731,
                        53.3666402221486
                    ],
                    [
                        -1.8571076618403,
                        53.3666671753923
                    ],
                    [
                        -1.85726980796225,
                        53.3666810764365
                    ],
                    [
                        -1.85779715350321,
                        53.3668672726909
                    ],
                    [
                        -1.85798148520325,
                        53.3669661773065
                    ],
                    [
                        -1.85813172568675,
                        53.3670761835036
                    ],
                    [
                        -1.85848119581394,
                        53.3674130609406
                    ],
                    [
                        -1.8586101774457,
                        53.3674884362004
                    ],
                    [
                        -1.85916654558414,
                        53.3677205285446
                    ],
                    [
                        -1.85933950285303,
                        53.3678181475754
                    ],
                    [
                        -1.85962409818593,
                        53.3680333593579
                    ],
                    [
                        -1.85980964798208,
                        53.3682526351071
                    ],
                    [
                        -1.86001476615986,
                        53.3683739254124
                    ],
                    [
                        -1.86016582896714,
                        53.3684382589352
                    ],
                    [
                        -1.86045877770803,
                        53.368493787109
                    ],
                    [
                        -1.86106116989019,
                        53.3687292553771
                    ],
                    [
                        -1.86257490705574,
                        53.3694178073211
                    ],
                    [
                        -1.86366720015858,
                        53.3699477209581
                    ],
                    [
                        -1.86394663855374,
                        53.3701077759571
                    ],
                    [
                        -1.86413063432643,
                        53.3702370790264
                    ],
                    [
                        -1.86449733360752,
                        53.3703947086184
                    ],
                    [
                        -1.86489203057045,
                        53.3706118452723
                    ],
                    [
                        -1.86506850366339,
                        53.3706828869411
                    ],
                    [
                        -1.86571659153504,
                        53.3708429373632
                    ],
                    [
                        -1.86640373553261,
                        53.3710548982914
                    ],
                    [
                        -1.86723664388114,
                        53.3711975037095
                    ],
                    [
                        -1.86785978668373,
                        53.3713297643466
                    ],
                    [
                        -1.8680308778965,
                        53.37138722022
                    ],
                    [
                        -1.86826063189698,
                        53.3715075787191
                    ],
                    [
                        -1.86843560623804,
                        53.3716559695309
                    ],
                    [
                        -1.86859612454558,
                        53.371898763036
                    ],
                    [
                        -1.86865878161458,
                        53.3721186665462
                    ],
                    [
                        -1.86880753588416,
                        53.3722356120247
                    ],
                    [
                        -1.86883545102101,
                        53.3723938309398
                    ],
                    [
                        -1.86878034029871,
                        53.3725956452193
                    ],
                    [
                        -1.8688181213183,
                        53.3727058713964
                    ],
                    [
                        -1.86888456767403,
                        53.3727343750653
                    ],
                    [
                        -1.86898588888668,
                        53.3727451050762
                    ],
                    [
                        -1.86929413367958,
                        53.3727128097585
                    ],
                    [
                        -1.86938562088186,
                        53.3727170982619
                    ],
                    [
                        -1.86942529023105,
                        53.3727332140137
                    ],
                    [
                        -1.8694971282267,
                        53.3728887813718
                    ],
                    [
                        -1.86951096460989,
                        53.3732010922596
                    ],
                    [
                        -1.86965219793101,
                        53.3733396810669
                    ],
                    [
                        -1.86978017054422,
                        53.3734073227676
                    ],
                    [
                        -1.86997464945606,
                        53.3734746428601
                    ],
                    [
                        -1.87026752436593,
                        53.3735250044429
                    ],
                    [
                        -1.87056024330608,
                        53.3735471850271
                    ],
                    [
                        -1.8707993412909,
                        53.3735202194975
                    ],
                    [
                        -1.87093417995369,
                        53.3734671192179
                    ],
                    [
                        -1.87112364809121,
                        53.3733425662072
                    ],
                    [
                        -1.87124913290998,
                        53.3732209346238
                    ],
                    [
                        -1.87131389333503,
                        53.3729659818956
                    ],
                    [
                        -1.87181975786814,
                        53.3728584950992
                    ],
                    [
                        -1.87280921278913,
                        53.3729530070621
                    ],
                    [
                        -1.87365890391746,
                        53.3728956469347
                    ],
                    [
                        -1.87431920295871,
                        53.3727869362149
                    ],
                    [
                        -1.87469426011937,
                        53.3727906406051
                    ],
                    [
                        -1.87506973084269,
                        53.3728601218148
                    ],
                    [
                        -1.87530162258192,
                        53.3728738984898
                    ],
                    [
                        -1.87552692380708,
                        53.3728783601853
                    ],
                    [
                        -1.87608664546105,
                        53.3728571989928
                    ],
                    [
                        -1.87684503747424,
                        53.3727872176786
                    ],
                    [
                        -1.87756633063907,
                        53.3727415679761
                    ],
                    [
                        -1.87773415052885,
                        53.3727180616736
                    ],
                    [
                        -1.87892265882308,
                        53.3724954199577
                    ],
                    [
                        -1.8795165663301,
                        53.3720611789281
                    ],
                    [
                        -1.87978600394514,
                        53.3718495113717
                    ],
                    [
                        -1.88006720852344,
                        53.3717986356236
                    ],
                    [
                        -1.8801587369991,
                        53.3718425771511
                    ],
                    [
                        -1.88020124098225,
                        53.3719376263261
                    ],
                    [
                        -1.88131021638599,
                        53.3731453525455
                    ],
                    [
                        -1.88149431240636,
                        53.3732816839927
                    ],
                    [
                        -1.88158348705812,
                        53.3733718270008
                    ],
                    [
                        -1.88205515487133,
                        53.3740264580333
                    ],
                    [
                        -1.88196073290316,
                        53.3741794019356
                    ],
                    [
                        -1.88193128950888,
                        53.3744123057308
                    ],
                    [
                        -1.88199958816846,
                        53.3745683671674
                    ],
                    [
                        -1.88198662620917,
                        53.3747364121088
                    ],
                    [
                        -1.88208960703111,
                        53.3748807739531
                    ],
                    [
                        -1.88199423826812,
                        53.3749780227816
                    ],
                    [
                        -1.88188372534614,
                        53.3751694065913
                    ],
                    [
                        -1.88185411771529,
                        53.3753057844974
                    ],
                    [
                        -1.88186765157314,
                        53.3757877484301
                    ],
                    [
                        -1.88192558076035,
                        53.3761521962596
                    ],
                    [
                        -1.88208731643711,
                        53.3764502208894
                    ],
                    [
                        -1.88216471224701,
                        53.3772178335197
                    ],
                    [
                        -1.88217426293403,
                        53.3773886923975
                    ],
                    [
                        -1.88219598089877,
                        53.3776859318382
                    ],
                    [
                        -1.88227494671644,
                        53.3779046386109
                    ],
                    [
                        -1.88267872685449,
                        53.3785422321665
                    ],
                    [
                        -1.88284521921667,
                        53.3787087259858
                    ],
                    [
                        -1.88299602962418,
                        53.378808797561
                    ],
                    [
                        -1.88320591820294,
                        53.3791061700346
                    ],
                    [
                        -1.88326089271641,
                        53.3793534282814
                    ],
                    [
                        -1.88330819626567,
                        53.3795056077759
                    ],
                    [
                        -1.88374031446972,
                        53.3799886657398
                    ],
                    [
                        -1.88379515762144,
                        53.3802857957685
                    ],
                    [
                        -1.88379414279094,
                        53.3806590731067
                    ],
                    [
                        -1.88374526644416,
                        53.3810846030898
                    ],
                    [
                        -1.88379414884105,
                        53.381568636512
                    ],
                    [
                        -1.88379311465228,
                        53.3819490129199
                    ],
                    [
                        -1.88382841860415,
                        53.3826869772308
                    ],
                    [
                        -1.88391518460819,
                        53.3829152154681
                    ],
                    [
                        -1.88419690709815,
                        53.3831532572992
                    ],
                    [
                        -1.88450245070557,
                        53.3833841332627
                    ],
                    [
                        -1.88477166847026,
                        53.3838027806209
                    ],
                    [
                        -1.88483878149712,
                        53.3839669287349
                    ],
                    [
                        -1.88482161561663,
                        53.3844494607115
                    ],
                    [
                        -1.88464572258767,
                        53.3848153804864
                    ],
                    [
                        -1.8843544703309,
                        53.385162228211
                    ],
                    [
                        -1.88416684994602,
                        53.3854164404234
                    ],
                    [
                        -1.88399865205613,
                        53.3857753582433
                    ],
                    [
                        -1.88371064432538,
                        53.3863836101788
                    ],
                    [
                        -1.88352581471435,
                        53.3871109370064
                    ],
                    [
                        -1.88341386398608,
                        53.3872962091152
                    ],
                    [
                        -1.88290388946562,
                        53.3876951382743
                    ],
                    [
                        -1.88256133988441,
                        53.3878849470098
                    ],
                    [
                        -1.88221094619135,
                        53.3880414983614
                    ],
                    [
                        -1.88188444962285,
                        53.3882075974206
                    ],
                    [
                        -1.88179825038912,
                        53.3882484858606
                    ],
                    [
                        -1.8816534020911,
                        53.3883310160463
                    ],
                    [
                        -1.88137379219753,
                        53.3884388656028
                    ],
                    [
                        -1.88117102404539,
                        53.3884725425429
                    ],
                    [
                        -1.88084395126193,
                        53.3885843697478
                    ],
                    [
                        -1.88070114624233,
                        53.3885877709217
                    ],
                    [
                        -1.88061803542305,
                        53.3885547612413
                    ],
                    [
                        -1.88053926147222,
                        53.3885699920342
                    ],
                    [
                        -1.8804945617701,
                        53.3886114197697
                    ],
                    [
                        -1.88046767756996,
                        53.3887684895992
                    ],
                    [
                        -1.8804719963621,
                        53.3889575008369
                    ],
                    [
                        -1.88053276022911,
                        53.3895846868841
                    ],
                    [
                        -1.88042328121364,
                        53.3896921518275
                    ],
                    [
                        -1.88027694987724,
                        53.3897469320665
                    ],
                    [
                        -1.87966584943856,
                        53.390435622622
                    ],
                    [
                        -1.87966317281408,
                        53.3906492230948
                    ],
                    [
                        -1.87958481742461,
                        53.3908585660424
                    ],
                    [
                        -1.87896381965753,
                        53.3916168197443
                    ],
                    [
                        -1.87887748004263,
                        53.3917504803844
                    ],
                    [
                        -1.87886109230816,
                        53.3919156258108
                    ],
                    [
                        -1.87873458301832,
                        53.3921506914391
                    ],
                    [
                        -1.87871018515889,
                        53.3923780537874
                    ],
                    [
                        -1.87863773660637,
                        53.3925083126496
                    ],
                    [
                        -1.878620589869,
                        53.3925871563533
                    ],
                    [
                        -1.87862712933576,
                        53.3926861934673
                    ],
                    [
                        -1.87867824048985,
                        53.3927788911547
                    ],
                    [
                        -1.87866914425475,
                        53.3928525745958
                    ],
                    [
                        -1.8787284315995,
                        53.3929743522156
                    ],
                    [
                        -1.8785336674321,
                        53.3932711474739
                    ],
                    [
                        -1.87831399040025,
                        53.3935475679159
                    ],
                    [
                        -1.87816465531267,
                        53.3936919376743
                    ],
                    [
                        -1.87816883411262,
                        53.3938116739271
                    ],
                    [
                        -1.87809546275503,
                        53.3939076500545
                    ],
                    [
                        -1.87807246170759,
                        53.3940671419746
                    ],
                    [
                        -1.87795018858432,
                        53.3941768485776
                    ],
                    [
                        -1.87783419527194,
                        53.3943525679819
                    ],
                    [
                        -1.87766705833875,
                        53.3945195826769
                    ],
                    [
                        -1.87759715488238,
                        53.3946466902772
                    ],
                    [
                        -1.87749864042325,
                        53.394749507586
                    ],
                    [
                        -1.87745943600186,
                        53.3948818535547
                    ],
                    [
                        -1.87758685528598,
                        53.3951657505369
                    ],
                    [
                        -1.87750972081241,
                        53.3954358252445
                    ],
                    [
                        -1.87736110374859,
                        53.3955588873333
                    ],
                    [
                        -1.87733074131322,
                        53.3957035584019
                    ],
                    [
                        -1.87713785053315,
                        53.3959467553551
                    ],
                    [
                        -1.87699455755319,
                        53.3962054722125
                    ],
                    [
                        -1.87685763621865,
                        53.3967046399779
                    ],
                    [
                        -1.87680368624462,
                        53.3967809907581
                    ],
                    [
                        -1.87667005073473,
                        53.3968985726672
                    ],
                    [
                        -1.87638949375365,
                        53.3970469720617
                    ],
                    [
                        -1.87633763381038,
                        53.3970996291772
                    ],
                    [
                        -1.87631658407965,
                        53.3971510677753
                    ],
                    [
                        -1.87631572227279,
                        53.3973001527145
                    ],
                    [
                        -1.8764231255546,
                        53.3973497419017
                    ],
                    [
                        -1.87654213534191,
                        53.3973480606005
                    ],
                    [
                        -1.87686349525304,
                        53.3972935989524
                    ],
                    [
                        -1.87721223049542,
                        53.3972596736655
                    ],
                    [
                        -1.87745077562137,
                        53.3972071191909
                    ],
                    [
                        -1.87784877330528,
                        53.3972116657647
                    ],
                    [
                        -1.87887273726561,
                        53.3973929122425
                    ],
                    [
                        -1.87916430053882,
                        53.3973939724789
                    ],
                    [
                        -1.87967741165511,
                        53.3973253786424
                    ],
                    [
                        -1.88001460203815,
                        53.3973521727787
                    ],
                    [
                        -1.88022482962297,
                        53.3974062065344
                    ],
                    [
                        -1.88034401621627,
                        53.397455760826
                    ],
                    [
                        -1.88045197363527,
                        53.3975192675001
                    ],
                    [
                        -1.8806259544312,
                        53.3976825363246
                    ],
                    [
                        -1.88075198141717,
                        53.3977317473665
                    ],
                    [
                        -1.88093873741022,
                        53.397750751508
                    ],
                    [
                        -1.88144983359706,
                        53.3977313396686
                    ],
                    [
                        -1.88189311502304,
                        53.3978030574934
                    ],
                    [
                        -1.88220124526318,
                        53.3978842082857
                    ],
                    [
                        -1.8826461992522,
                        53.398045558723
                    ],
                    [
                        -1.88273296152348,
                        53.3980623237074
                    ],
                    [
                        -1.88319722715986,
                        53.3982614060153
                    ],
                    [
                        -1.8834355089659,
                        53.3983361054387
                    ],
                    [
                        -1.88355303612173,
                        53.3983948259137
                    ],
                    [
                        -1.88373751144027,
                        53.3984377257937
                    ],
                    [
                        -1.88391706794378,
                        53.398424131221
                    ],
                    [
                        -1.88417147913935,
                        53.3984958003772
                    ],
                    [
                        -1.88432139764596,
                        53.3985550943072
                    ],
                    [
                        -1.88449116137098,
                        53.3985847144246
                    ],
                    [
                        -1.88491425409084,
                        53.3987632151124
                    ],
                    [
                        -1.88537863928747,
                        53.3989075595824
                    ],
                    [
                        -1.88614621385227,
                        53.3992082982902
                    ],
                    [
                        -1.88658209008828,
                        53.3993481427723
                    ],
                    [
                        -1.88712971109176,
                        53.3994966615302
                    ],
                    [
                        -1.88757400281334,
                        53.3995956762621
                    ],
                    [
                        -1.88801740188387,
                        53.3996584943445
                    ],
                    [
                        -1.88831024571965,
                        53.399672768169
                    ],
                    [
                        -1.88861092682913,
                        53.3996639965462
                    ],
                    [
                        -1.88926391738237,
                        53.3995759539732
                    ],
                    [
                        -1.88980583792666,
                        53.3995259279637
                    ],
                    [
                        -1.89087460261956,
                        53.3998238332948
                    ],
                    [
                        -1.89124281415777,
                        53.3999047133876
                    ],
                    [
                        -1.89222595871204,
                        53.4000297790168
                    ],
                    [
                        -1.892616873833,
                        53.4001550346255
                    ],
                    [
                        -1.89282722447911,
                        53.400249205267
                    ],
                    [
                        -1.89318196536824,
                        53.4004410775925
                    ],
                    [
                        -1.8933550619867,
                        53.4005038521803
                    ],
                    [
                        -1.8936777853593,
                        53.4005720221168
                    ],
                    [
                        -1.8939931228281,
                        53.400608401173
                    ],
                    [
                        -1.89436902256721,
                        53.4006129998663
                    ],
                    [
                        -1.89511324957226,
                        53.4005462869519
                    ],
                    [
                        -1.89527156452728,
                        53.4005203864672
                    ],
                    [
                        -1.89527615266815,
                        53.4009291793513
                    ],
                    [
                        -1.89513196710484,
                        53.401342558437
                    ],
                    [
                        -1.89535952017249,
                        53.4020126037872
                    ],
                    [
                        -1.89547183235379,
                        53.4022144899322
                    ],
                    [
                        -1.89561463482475,
                        53.4023355524284
                    ],
                    [
                        -1.89571113056393,
                        53.4023853969518
                    ],
                    [
                        -1.89694106648156,
                        53.4029407746202
                    ],
                    [
                        -1.89723712363276,
                        53.4031141874974
                    ],
                    [
                        -1.89733361558304,
                        53.4031502332968
                    ],
                    [
                        -1.89827257808811,
                        53.4033234400797
                    ],
                    [
                        -1.89896289070378,
                        53.4034866830257
                    ],
                    [
                        -1.89964687752887,
                        53.4038369986361
                    ],
                    [
                        -1.89995470487547,
                        53.4040573572101
                    ],
                    [
                        -1.90039124159041,
                        53.4044209400943
                    ],
                    [
                        -1.90042787006889,
                        53.4044770922204
                    ],
                    [
                        -1.90054137587408,
                        53.4050243669327
                    ],
                    [
                        -1.90055059381035,
                        53.4051746700224
                    ],
                    [
                        -1.90065729832572,
                        53.4054573659963
                    ],
                    [
                        -1.90069265090245,
                        53.4057587528632
                    ],
                    [
                        -1.90095544752401,
                        53.4061625561407
                    ],
                    [
                        -1.90109437948434,
                        53.4063429034284
                    ],
                    [
                        -1.90115526251255,
                        53.406388742101
                    ],
                    [
                        -1.90138596303117,
                        53.4065462717671
                    ],
                    [
                        -1.90306199896653,
                        53.4070218425906
                    ],
                    [
                        -1.90469844224935,
                        53.4077263573049
                    ],
                    [
                        -1.90484874143686,
                        53.407878455563
                    ],
                    [
                        -1.9049734916271,
                        53.408094917306
                    ],
                    [
                        -1.90512440143218,
                        53.4082954944094
                    ],
                    [
                        -1.90541324603264,
                        53.4085161266149
                    ],
                    [
                        -1.90659556319473,
                        53.4092446150113
                    ],
                    [
                        -1.90698902819566,
                        53.4094383223644
                    ],
                    [
                        -1.90747048160428,
                        53.4095928380431
                    ],
                    [
                        -1.90855005772656,
                        53.4099776269454
                    ],
                    [
                        -1.90907693812022,
                        53.4102538960314
                    ],
                    [
                        -1.90951615583313,
                        53.4105334296315
                    ],
                    [
                        -1.9091720714642,
                        53.41091421104
                    ],
                    [
                        -1.90881991828448,
                        53.4112192390299
                    ],
                    [
                        -1.9086381188584,
                        53.4114356611525
                    ],
                    [
                        -1.90825031300053,
                        53.4118217457245
                    ],
                    [
                        -1.9079391348266,
                        53.4120980517262
                    ],
                    [
                        -1.90751491804794,
                        53.4124053197464
                    ],
                    [
                        -1.9071283176387,
                        53.412813610379
                    ],
                    [
                        -1.90662884764169,
                        53.4132566406375
                    ],
                    [
                        -1.90651789328234,
                        53.4134479008968
                    ],
                    [
                        -1.90632514741165,
                        53.4136498753299
                    ],
                    [
                        -1.90604031573851,
                        53.4137932620947
                    ],
                    [
                        -1.90556300148115,
                        53.4142208359436
                    ],
                    [
                        -1.90507532367357,
                        53.414816962201
                    ],
                    [
                        -1.90440175760669,
                        53.4155525273349
                    ],
                    [
                        -1.90399743335771,
                        53.4158333246786
                    ],
                    [
                        -1.90366711450709,
                        53.4161210626114
                    ],
                    [
                        -1.90348962599336,
                        53.4163870383619
                    ],
                    [
                        -1.9032776053936,
                        53.4165574794415
                    ],
                    [
                        -1.90307696910604,
                        53.4168215995368
                    ],
                    [
                        -1.90287166754458,
                        53.4170235985897
                    ],
                    [
                        -1.90282366552097,
                        53.4171221600958
                    ],
                    [
                        -1.90252856643732,
                        53.4172628074712
                    ],
                    [
                        -1.90229320504963,
                        53.417439584484
                    ],
                    [
                        -1.90190473742389,
                        53.4178304456147
                    ],
                    [
                        -1.90117028537256,
                        53.4182922413038
                    ],
                    [
                        -1.90099513206043,
                        53.4183509958493
                    ],
                    [
                        -1.9003692456801,
                        53.4184119966716
                    ],
                    [
                        -1.8990426668291,
                        53.4190397054085
                    ],
                    [
                        -1.89832450342024,
                        53.4194674289847
                    ],
                    [
                        -1.89783418705819,
                        53.4197085532555
                    ],
                    [
                        -1.89744103131239,
                        53.4198694157591
                    ],
                    [
                        -1.89692080892287,
                        53.4200195191136
                    ],
                    [
                        -1.89638865911051,
                        53.4201004586012
                    ],
                    [
                        -1.89519308524202,
                        53.420190969273
                    ],
                    [
                        -1.89435926234865,
                        53.4202277204856
                    ],
                    [
                        -1.89386380281463,
                        53.4201404674003
                    ],
                    [
                        -1.89331807392998,
                        53.4201995283255
                    ],
                    [
                        -1.89280170793009,
                        53.4202092840798
                    ],
                    [
                        -1.89238540283677,
                        53.4202860496043
                    ],
                    [
                        -1.89143728319883,
                        53.4202846617724
                    ],
                    [
                        -1.89126226921172,
                        53.4202955985743
                    ],
                    [
                        -1.89109195262979,
                        53.4203254619956
                    ],
                    [
                        -1.89093460964162,
                        53.4203728367051
                    ],
                    [
                        -1.89061730100013,
                        53.4205388035553
                    ],
                    [
                        -1.89031144366757,
                        53.4206462235016
                    ],
                    [
                        -1.88934013383209,
                        53.4211808391598
                    ],
                    [
                        -1.88873101963581,
                        53.4213341325106
                    ],
                    [
                        -1.88816315807047,
                        53.4215464483246
                    ],
                    [
                        -1.88786303791553,
                        53.4216151142917
                    ],
                    [
                        -1.88751144597423,
                        53.4217967419118
                    ],
                    [
                        -1.88714470420311,
                        53.4219015636216
                    ],
                    [
                        -1.88707222812783,
                        53.4220170282339
                    ],
                    [
                        -1.88698057886855,
                        53.4221054957227
                    ],
                    [
                        -1.88663851713749,
                        53.4222233491052
                    ],
                    [
                        -1.88640939700892,
                        53.42240482047
                    ],
                    [
                        -1.88624138372288,
                        53.4224473664275
                    ],
                    [
                        -1.88611845808409,
                        53.4225392758227
                    ],
                    [
                        -1.88604580360018,
                        53.4226243036531
                    ],
                    [
                        -1.88578255575711,
                        53.422781866987
                    ],
                    [
                        -1.8855001557547,
                        53.423073614317
                    ],
                    [
                        -1.88503359815336,
                        53.423277578017
                    ],
                    [
                        -1.88468721622322,
                        53.4235458613473
                    ],
                    [
                        -1.8844909964541,
                        53.4236357498112
                    ],
                    [
                        -1.88427735016579,
                        53.4237106561681
                    ],
                    [
                        -1.88404840258578,
                        53.4237621619506
                    ],
                    [
                        -1.88373271816481,
                        53.4237862060039
                    ],
                    [
                        -1.88338164906568,
                        53.4238907095484
                    ],
                    [
                        -1.88294518653119,
                        53.4241096089716
                    ],
                    [
                        -1.88210922334973,
                        53.4244254042697
                    ],
                    [
                        -1.88185609094254,
                        53.4244818634842
                    ],
                    [
                        -1.88131293865842,
                        53.4247020278525
                    ],
                    [
                        -1.88109690725772,
                        53.4248377917947
                    ],
                    [
                        -1.88064786023016,
                        53.4252467960049
                    ],
                    [
                        -1.88014723210952,
                        53.4254625022401
                    ],
                    [
                        -1.87979797802669,
                        53.4255583950507
                    ],
                    [
                        -1.87948964728743,
                        53.4256826058209
                    ],
                    [
                        -1.87916211230616,
                        53.4257925190966
                    ],
                    [
                        -1.87809075893583,
                        53.4259792434231
                    ],
                    [
                        -1.87788418420712,
                        53.4259966550665
                    ],
                    [
                        -1.87750203628675,
                        53.4259592117644
                    ],
                    [
                        -1.8768648386822,
                        53.4259767532717
                    ],
                    [
                        -1.87650875555216,
                        53.4260649424792
                    ],
                    [
                        -1.87621223107683,
                        53.4260646365507
                    ],
                    [
                        -1.87588651947658,
                        53.4259049002783
                    ],
                    [
                        -1.87449234285489,
                        53.4260805585447
                    ],
                    [
                        -1.87425491412331,
                        53.4261511534076
                    ],
                    [
                        -1.873838890894,
                        53.4264518030479
                    ],
                    [
                        -1.87348148309462,
                        53.4269827553525
                    ],
                    [
                        -1.87321371199253,
                        53.427283559211
                    ],
                    [
                        -1.8724714290702,
                        53.4276015693351
                    ],
                    [
                        -1.87235228422734,
                        53.4277785518562
                    ],
                    [
                        -1.87202551152264,
                        53.4279730236283
                    ],
                    [
                        -1.87152033177924,
                        53.4283267026724
                    ],
                    [
                        -1.87122304469199,
                        53.4285743375513
                    ],
                    [
                        -1.87071693874178,
                        53.4292290989502
                    ],
                    [
                        -1.87041904892695,
                        53.4296715514028
                    ],
                    [
                        -1.86967594457159,
                        53.4302374962004
                    ],
                    [
                        -1.86955618651471,
                        53.4306092963206
                    ],
                    [
                        -1.86958519222119,
                        53.4308218599431
                    ],
                    [
                        -1.86931791203998,
                        53.4309455452439
                    ],
                    [
                        -1.86934729650127,
                        53.4310341319294
                    ],
                    [
                        -1.86925729789732,
                        53.4313705422911
                    ],
                    [
                        -1.86936191457219,
                        53.4316983004492
                    ],
                    [
                        -1.86913720698623,
                        53.4318486071135
                    ],
                    [
                        -1.86906350633529,
                        53.4326299016029
                    ],
                    [
                        -1.86897633287088,
                        53.4327905286279
                    ],
                    [
                        -1.86897253564828,
                        53.4329149135067
                    ],
                    [
                        -1.86851307173494,
                        53.4338228562457
                    ],
                    [
                        -1.86783891883865,
                        53.4346228154758
                    ],
                    [
                        -1.86710369366865,
                        53.4355468044272
                    ],
                    [
                        -1.86679669014038,
                        53.435875658775
                    ],
                    [
                        -1.8667218827385,
                        53.4359744255718
                    ],
                    [
                        -1.86649228480882,
                        53.4364005837507
                    ],
                    [
                        -1.86626421754421,
                        53.4367010104391
                    ],
                    [
                        -1.86567838151765,
                        53.4372045812869
                    ],
                    [
                        -1.86505052704318,
                        53.4378011057496
                    ],
                    [
                        -1.86464274853519,
                        53.4380833075306
                    ],
                    [
                        -1.86395180787153,
                        53.4384434755164
                    ],
                    [
                        -1.8632250238223,
                        53.438976372486
                    ],
                    [
                        -1.86268496887596,
                        53.439219729146
                    ],
                    [
                        -1.86242512235615,
                        53.4393926543901
                    ],
                    [
                        -1.86165110207331,
                        53.4397709440238
                    ],
                    [
                        -1.85996856206667,
                        53.4406760780543
                    ],
                    [
                        -1.85908669574149,
                        53.4411156063441
                    ],
                    [
                        -1.85839376974057,
                        53.441416324967
                    ],
                    [
                        -1.85767764425866,
                        53.4417571284811
                    ],
                    [
                        -1.85672706352741,
                        53.4422906553238
                    ],
                    [
                        -1.85604876890137,
                        53.4426945745043
                    ],
                    [
                        -1.85487902781798,
                        53.443492958823
                    ],
                    [
                        -1.85355124791322,
                        53.4444397656401
                    ],
                    [
                        -1.85316160566887,
                        53.4447673554255
                    ],
                    [
                        -1.85294651870709,
                        53.445135496785
                    ],
                    [
                        -1.85278284677363,
                        53.4455506576084
                    ],
                    [
                        -1.85269291682004,
                        53.4456391446437
                    ],
                    [
                        -1.85253779583267,
                        53.4461159504624
                    ],
                    [
                        -1.8525277561359,
                        53.4462148472487
                    ],
                    [
                        -1.85258492544839,
                        53.4462762288729
                    ],
                    [
                        -1.85273260426042,
                        53.4463237518791
                    ],
                    [
                        -1.85275679301277,
                        53.4463656966512
                    ],
                    [
                        -1.8526796672352,
                        53.4464600742659
                    ],
                    [
                        -1.8525442769322,
                        53.4467624677308
                    ],
                    [
                        -1.85255154902589,
                        53.4467842512519
                    ],
                    [
                        -1.85270232130499,
                        53.4468729677649
                    ],
                    [
                        -1.85272550005987,
                        53.4469175278411
                    ],
                    [
                        -1.85270111121164,
                        53.446984389157
                    ],
                    [
                        -1.85233446934695,
                        53.4473989273914
                    ],
                    [
                        -1.85235211240997,
                        53.4475276235764
                    ],
                    [
                        -1.85244937747205,
                        53.4476554920324
                    ],
                    [
                        -1.85286990311536,
                        53.448046123155
                    ],
                    [
                        -1.85326790543511,
                        53.4481498168664
                    ],
                    [
                        -1.85344072964828,
                        53.4482579430611
                    ],
                    [
                        -1.85372363396345,
                        53.4483488197558
                    ],
                    [
                        -1.85384621172538,
                        53.4484202793638
                    ],
                    [
                        -1.85391957610224,
                        53.448538017998
                    ],
                    [
                        -1.85388225581578,
                        53.4486220164609
                    ],
                    [
                        -1.85378662041996,
                        53.4487677655398
                    ],
                    [
                        -1.8535482981759,
                        53.4488390451288
                    ],
                    [
                        -1.85349175839346,
                        53.4488813539299
                    ],
                    [
                        -1.85343708823962,
                        53.4490021459961
                    ],
                    [
                        -1.85348268313992,
                        53.4490733355952
                    ],
                    [
                        -1.85360549219448,
                        53.449142385915
                    ],
                    [
                        -1.85379133145179,
                        53.4492129610848
                    ],
                    [
                        -1.85420004649271,
                        53.4493034543861
                    ],
                    [
                        -1.85456492920336,
                        53.4494419481268
                    ],
                    [
                        -1.85493079192781,
                        53.4495325352077
                    ],
                    [
                        -1.85510893080388,
                        53.4495945437753
                    ],
                    [
                        -1.85543074439962,
                        53.4497570673645
                    ],
                    [
                        -1.85547668736221,
                        53.449830295195
                    ],
                    [
                        -1.85556134098556,
                        53.4501769188007
                    ],
                    [
                        -1.85558385360063,
                        53.4504057212486
                    ],
                    [
                        -1.8555669550748,
                        53.4507321691038
                    ],
                    [
                        -1.85560601080964,
                        53.4510035248775
                    ],
                    [
                        -1.85565020475468,
                        53.4510592481799
                    ],
                    [
                        -1.85581662046392,
                        53.4511374558373
                    ],
                    [
                        -1.85584453652791,
                        53.4511849610992
                    ],
                    [
                        -1.85585523096064,
                        53.4512943770491
                    ],
                    [
                        -1.8559903422847,
                        53.4514591569308
                    ],
                    [
                        -1.85599846243518,
                        53.4517026704435
                    ],
                    [
                        -1.85636014188147,
                        53.4520970967493
                    ],
                    [
                        -1.85646075882494,
                        53.4523076587933
                    ],
                    [
                        -1.85655906037512,
                        53.4524557077174
                    ],
                    [
                        -1.85684358123283,
                        53.4527077078279
                    ],
                    [
                        -1.85702459360676,
                        53.4528197314226
                    ],
                    [
                        -1.85769319226882,
                        53.4530855593026
                    ],
                    [
                        -1.85829308844946,
                        53.453263558647
                    ],
                    [
                        -1.85859248970607,
                        53.4533901768411
                    ],
                    [
                        -1.8592337246277,
                        53.4538702252654
                    ],
                    [
                        -1.85941521145821,
                        53.4539673581828
                    ],
                    [
                        -1.85997690859653,
                        53.4540571445139
                    ],
                    [
                        -1.86023279504716,
                        53.4541376211963
                    ],
                    [
                        -1.86065531715603,
                        53.4543072077408
                    ],
                    [
                        -1.86086610384153,
                        53.4543607937709
                    ],
                    [
                        -1.86165486859122,
                        53.4544457787232
                    ],
                    [
                        -1.86199332419049,
                        53.4545579413507
                    ],
                    [
                        -1.86219644995729,
                        53.454656800056
                    ],
                    [
                        -1.86236090965255,
                        53.4547649449273
                    ],
                    [
                        -1.86245035653948,
                        53.4548501503411
                    ],
                    [
                        -1.86254751592474,
                        53.4550118176504
                    ],
                    [
                        -1.86257022186506,
                        53.4551150994874
                    ],
                    [
                        -1.8625255980341,
                        53.4559238124993
                    ],
                    [
                        -1.86260101511446,
                        53.4565798458664
                    ],
                    [
                        -1.8623862521646,
                        53.4570833744232
                    ],
                    [
                        -1.86232467330801,
                        53.4572765185914
                    ],
                    [
                        -1.86231064823259,
                        53.4574246600504
                    ],
                    [
                        -1.86237034516935,
                        53.4575545740175
                    ],
                    [
                        -1.86264331874694,
                        53.4578611777101
                    ],
                    [
                        -1.86272665391353,
                        53.4580814399383
                    ],
                    [
                        -1.86275402523189,
                        53.4585665483579
                    ],
                    [
                        -1.862660714101,
                        53.4589305213609
                    ],
                    [
                        -1.86289313030562,
                        53.4596413568183
                    ],
                    [
                        -1.86286431588479,
                        53.4597752355666
                    ],
                    [
                        -1.86273531616752,
                        53.4598955987199
                    ],
                    [
                        -1.86172946225104,
                        53.4603564046487
                    ],
                    [
                        -1.86119045825535,
                        53.460627180552
                    ],
                    [
                        -1.86054332409805,
                        53.4608971064612
                    ],
                    [
                        -1.85995613458814,
                        53.4611936867513
                    ],
                    [
                        -1.85974859289948,
                        53.4613157022011
                    ],
                    [
                        -1.85972558264991,
                        53.4613631207876
                    ],
                    [
                        -1.85974482343842,
                        53.4614226450299
                    ],
                    [
                        -1.86030373602688,
                        53.4620248837939
                    ],
                    [
                        -1.86038456290066,
                        53.4621553760664
                    ],
                    [
                        -1.86042250694755,
                        53.4624328657166
                    ],
                    [
                        -1.86044878607832,
                        53.4624689327956
                    ],
                    [
                        -1.8608724813629,
                        53.4628347931265
                    ],
                    [
                        -1.86112894643044,
                        53.4631629431957
                    ],
                    [
                        -1.86107829388707,
                        53.4633108936032
                    ],
                    [
                        -1.86107069332835,
                        53.4634319825007
                    ],
                    [
                        -1.861106928989,
                        53.4636613916036
                    ],
                    [
                        -1.86116060556932,
                        53.4637595653545
                    ],
                    [
                        -1.8613255394902,
                        53.4639078454088
                    ],
                    [
                        -1.86154755277899,
                        53.4640224593578
                    ],
                    [
                        -1.86168012589548,
                        53.46411742433
                    ],
                    [
                        -1.86177575280008,
                        53.4643136687639
                    ],
                    [
                        -1.86222272593452,
                        53.4646341818595
                    ],
                    [
                        -1.86233675076247,
                        53.464782011858
                    ],
                    [
                        -1.86241773147213,
                        53.4649663625017
                    ],
                    [
                        -1.86243828751162,
                        53.4653386145118
                    ],
                    [
                        -1.86259270668635,
                        53.4657655070648
                    ],
                    [
                        -1.86285344558795,
                        53.4658256498462
                    ],
                    [
                        -1.86315712304164,
                        53.465929170763
                    ],
                    [
                        -1.86369593557807,
                        53.4659857881124
                    ],
                    [
                        -1.86381525968764,
                        53.4660128657022
                    ],
                    [
                        -1.8639918257496,
                        53.4661265362519
                    ],
                    [
                        -1.86412579464478,
                        53.4661753803732
                    ],
                    [
                        -1.86524748156817,
                        53.4661549656944
                    ],
                    [
                        -1.86613659767486,
                        53.4660996350357
                    ],
                    [
                        -1.866874683006,
                        53.4661427314933
                    ],
                    [
                        -1.86704018795389,
                        53.4661390969076
                    ],
                    [
                        -1.867348494259,
                        53.4661116471484
                    ],
                    [
                        -1.86811814442633,
                        53.4659391157343
                    ],
                    [
                        -1.86949707384952,
                        53.4656708180631
                    ],
                    [
                        -1.87017685512985,
                        53.4655608132481
                    ],
                    [
                        -1.87093725004325,
                        53.4653635183609
                    ],
                    [
                        -1.87140378189919,
                        53.4653009739326
                    ],
                    [
                        -1.87161424994626,
                        53.4652973956209
                    ],
                    [
                        -1.87269862576899,
                        53.4654260018442
                    ],
                    [
                        -1.87290952034311,
                        53.4654305894989
                    ],
                    [
                        -1.87318818654434,
                        53.4654136276992
                    ],
                    [
                        -1.87493538347613,
                        53.4652393643499
                    ],
                    [
                        -1.87567573483271,
                        53.4650133039337
                    ],
                    [
                        -1.87620245765932,
                        53.4649281765776
                    ],
                    [
                        -1.8768121958267,
                        53.4648868825593
                    ],
                    [
                        -1.87790512807396,
                        53.4647547217682
                    ],
                    [
                        -1.87846957975948,
                        53.4647360330246
                    ],
                    [
                        -1.87902847270928,
                        53.464688216158
                    ],
                    [
                        -1.8794240775662,
                        53.4646929983158
                    ],
                    [
                        -1.87946657057703,
                        53.4646275081238
                    ],
                    [
                        -1.87956030508344,
                        53.4646236824594
                    ],
                    [
                        -1.87969640760358,
                        53.4646624990522
                    ],
                    [
                        -1.87992632599872,
                        53.4647799270946
                    ],
                    [
                        -1.88004105871448,
                        53.464967406859
                    ],
                    [
                        -1.88012216384753,
                        53.4652585830716
                    ],
                    [
                        -1.88050127156902,
                        53.4657042271759
                    ],
                    [
                        -1.88069040954547,
                        53.4658697982917
                    ],
                    [
                        -1.88094485548014,
                        53.4660054871879
                    ],
                    [
                        -1.88186745772687,
                        53.4663856605085
                    ],
                    [
                        -1.88209408793904,
                        53.4665379652216
                    ],
                    [
                        -1.88255290538376,
                        53.4669022062747
                    ],
                    [
                        -1.88313253693577,
                        53.4673921524608
                    ],
                    [
                        -1.88344107825529,
                        53.4675943653746
                    ],
                    [
                        -1.88385308334466,
                        53.4677571448059
                    ],
                    [
                        -1.88434337780445,
                        53.4678832608141
                    ],
                    [
                        -1.88499333974753,
                        53.46800344826
                    ],
                    [
                        -1.8854636415223,
                        53.4681150745037
                    ],
                    [
                        -1.88671232265448,
                        53.4686043432897
                    ],
                    [
                        -1.88745183609815,
                        53.4688022997112
                    ],
                    [
                        -1.88788071585304,
                        53.4688660554856
                    ],
                    [
                        -1.88822999451458,
                        53.4688996890324
                    ],
                    [
                        -1.88945801925804,
                        53.4689567351965
                    ],
                    [
                        -1.89058003924004,
                        53.4689969535999
                    ],
                    [
                        -1.89102096344991,
                        53.4689829357805
                    ],
                    [
                        -1.89190243628436,
                        53.4690265938474
                    ],
                    [
                        -1.89270799694822,
                        53.4690157543792
                    ],
                    [
                        -1.89307653703445,
                        53.4690392079909
                    ],
                    [
                        -1.89374696672883,
                        53.4691823548428
                    ],
                    [
                        -1.89441808867301,
                        53.4693592168395
                    ],
                    [
                        -1.89588579100597,
                        53.4693371171058
                    ],
                    [
                        -1.89632254495633,
                        53.4693425971821
                    ],
                    [
                        -1.89671397915081,
                        53.4693788076483
                    ],
                    [
                        -1.89740650952139,
                        53.4695005245617
                    ],
                    [
                        -1.89807003234878,
                        53.4696514791467
                    ],
                    [
                        -1.89871660817276,
                        53.4696939613383
                    ],
                    [
                        -1.89904084211215,
                        53.4696839401575
                    ],
                    [
                        -1.89918327743145,
                        53.4697002759527
                    ],
                    [
                        -1.89941077207163,
                        53.469751122089
                    ],
                    [
                        -1.89998190156468,
                        53.4697778853015
                    ],
                    [
                        -1.90040432028536,
                        53.4698506070193
                    ],
                    [
                        -1.90078778118439,
                        53.4698507179603
                    ],
                    [
                        -1.90134445532378,
                        53.4699270365936
                    ],
                    [
                        -1.9026395107441,
                        53.4702598995173
                    ],
                    [
                        -1.90310840030714,
                        53.4704309423263
                    ],
                    [
                        -1.90327569963178,
                        53.4704484582138
                    ],
                    [
                        -1.90339544632386,
                        53.47053699272
                    ],
                    [
                        -1.9039036396469,
                        53.4707955888519
                    ],
                    [
                        -1.90471740848347,
                        53.4713032164949
                    ],
                    [
                        -1.90483842476773,
                        53.4713653344594
                    ],
                    [
                        -1.90508178424881,
                        53.4714543418272
                    ],
                    [
                        -1.90525729365657,
                        53.4716144322608
                    ],
                    [
                        -1.90540406960003,
                        53.4717926914641
                    ],
                    [
                        -1.90568467886233,
                        53.4719882523852
                    ],
                    [
                        -1.90576008969502,
                        53.4720867007322
                    ],
                    [
                        -1.90592436637964,
                        53.4724729768728
                    ],
                    [
                        -1.90594228313618,
                        53.4727202337289
                    ],
                    [
                        -1.90598649387212,
                        53.4728999110268
                    ],
                    [
                        -1.90614264043423,
                        53.4732868159234
                    ],
                    [
                        -1.90616771319054,
                        53.4734616945293
                    ],
                    [
                        -1.90624814842674,
                        53.4737227470508
                    ],
                    [
                        -1.90653903491632,
                        53.4743163113929
                    ],
                    [
                        -1.90662987866226,
                        53.4747251791287
                    ],
                    [
                        -1.90625615277345,
                        53.4749772737083
                    ],
                    [
                        -1.90591804236466,
                        53.4753220836297
                    ],
                    [
                        -1.9059422577542,
                        53.4758301640885
                    ],
                    [
                        -1.9060309507886,
                        53.4764554320735
                    ],
                    [
                        -1.90616306720042,
                        53.4764639845497
                    ],
                    [
                        -1.90634126932777,
                        53.4766523205549
                    ],
                    [
                        -1.90648283793541,
                        53.4767514257866
                    ],
                    [
                        -1.90676194092061,
                        53.4769130488463
                    ],
                    [
                        -1.90691961711555,
                        53.4769808009815
                    ],
                    [
                        -1.90745436127615,
                        53.4771321857307
                    ],
                    [
                        -1.90788245138147,
                        53.4771539056563
                    ],
                    [
                        -1.90806323508519,
                        53.4771764676614
                    ],
                    [
                        -1.90836607864971,
                        53.4772520716026
                    ],
                    [
                        -1.908314015358,
                        53.4774323422002
                    ],
                    [
                        -1.90830523148574,
                        53.4775981466217
                    ],
                    [
                        -1.90836838659968,
                        53.4778504799362
                    ],
                    [
                        -1.90848388081613,
                        53.4778276116256
                    ],
                    [
                        -1.90867975434171,
                        53.4778277607943
                    ],
                    [
                        -1.90932724198407,
                        53.4780170083557
                    ],
                    [
                        -1.90997481136449,
                        53.4781702987982
                    ],
                    [
                        -1.91032130288204,
                        53.4781975233778
                    ],
                    [
                        -1.91051717812204,
                        53.478197669536
                    ],
                    [
                        -1.91087886916314,
                        53.4781619849149
                    ],
                    [
                        -1.91107472548211,
                        53.4781711185614
                    ],
                    [
                        -1.91187292146011,
                        53.4783514754335
                    ],
                    [
                        -1.91283692128148,
                        53.4785049822014
                    ],
                    [
                        -1.91342442344721,
                        53.4785683261616
                    ],
                    [
                        -1.91381603192607,
                        53.4786405152044
                    ],
                    [
                        -1.91458400514352,
                        53.4788747627419
                    ],
                    [
                        -1.91556291612974,
                        53.4791181422513
                    ],
                    [
                        -1.91456857711526,
                        53.4790545200574
                    ],
                    [
                        -1.91438771135331,
                        53.4790813564854
                    ],
                    [
                        -1.91411622203632,
                        53.4792159888275
                    ],
                    [
                        -1.91375437917085,
                        53.4793235904444
                    ],
                    [
                        -1.91471853377244,
                        53.4794141632155
                    ],
                    [
                        -1.91526081220992,
                        53.4794954428351
                    ],
                    [
                        -1.91587832532848,
                        53.4796307031986
                    ],
                    [
                        -1.91702290324907,
                        53.4799281171217
                    ],
                    [
                        -1.91727891865789,
                        53.4800002010353
                    ],
                    [
                        -1.91738423757317,
                        53.4800811692438
                    ],
                    [
                        -1.91742933704678,
                        53.4801351307343
                    ],
                    [
                        -1.91744416123534,
                        53.480260978699
                    ],
                    [
                        -1.91745459707864,
                        53.4826519030474
                    ],
                    [
                        -1.91748464784673,
                        53.4826968657396
                    ],
                    [
                        -1.9176651969867,
                        53.4828408041802
                    ],
                    [
                        -1.9177495570303,
                        53.4828786348677
                    ],
                    [
                        -1.91771809747676,
                        53.4829035948023
                    ],
                    [
                        -1.91775119488747,
                        53.4830207660907
                    ],
                    [
                        -1.91779934548324,
                        53.4830572470486
                    ],
                    [
                        -1.91775727744864,
                        53.4831093959576
                    ],
                    [
                        -1.9178154030235,
                        53.4831111776984
                    ],
                    [
                        -1.9177966371913,
                        53.4831331972413
                    ],
                    [
                        -1.91784199913207,
                        53.4832905496818
                    ],
                    [
                        -1.91711349884707,
                        53.4835183286204
                    ],
                    [
                        -1.91288526173035,
                        53.4840229911381
                    ],
                    [
                        -1.91186714127023,
                        53.4842251039065
                    ],
                    [
                        -1.90986140661294,
                        53.4844165446839
                    ],
                    [
                        -1.90889507500903,
                        53.4844867796251
                    ],
                    [
                        -1.9082508217478,
                        53.4845064481748
                    ],
                    [
                        -1.90821301109652,
                        53.4846628822546
                    ],
                    [
                        -1.90766865166759,
                        53.4846519061248
                    ],
                    [
                        -1.9068890980898,
                        53.4847262502254
                    ],
                    [
                        -1.90649914910579,
                        53.4848081011517
                    ],
                    [
                        -1.90614489716726,
                        53.4849317190802
                    ],
                    [
                        -1.90571596351346,
                        53.485145809439
                    ],
                    [
                        -1.90502276538138,
                        53.4857311757187
                    ],
                    [
                        -1.90490359311656,
                        53.4858061174619
                    ],
                    [
                        -1.90454421596043,
                        53.485975672595
                    ],
                    [
                        -1.90448519099357,
                        53.4860260164314
                    ],
                    [
                        -1.90429517708625,
                        53.486085362018
                    ],
                    [
                        -1.90264118972156,
                        53.4869006974405
                    ],
                    [
                        -1.90052400171648,
                        53.4875916534084
                    ],
                    [
                        -1.89821565865495,
                        53.4882998275588
                    ]
                ]
            }
        }
    ]
}