{
    "type": "FeatureCollection",
    "features": [
        {
            "type": "Feature",
            "properties": {
                "name": "Pennine Way"
            },
            "geometry": {
                "type": "LineString",
                "coordinates": [
                    [
                        -2.29531239758697,
                        54.1484630872054
                    ],
                    [
                        -2.29552890672356,
                        54.1487681270251
                    ],
                    [
                        -2.29581241912004,
                        54.1494000351964
                    ],
                    [
                        -2.29582857501661,
                        54.1494585303969
                    ],
                    [
                        -2.29577943464061,
                        54.1495494150175
                    ],
                    [
                        -2.29579532125138,
                        54.1496302625475
                    ],
                    [
                        -2.29584157136741,
                        54.1496750857873
                    ],
                    [
                        -2.2953487076595,
                        54.1497154597598
                    ],
                    [
                        -2.2952687442961,
                        54.1497479640113
                    ],
                    [
                        -2.2951045187219,
                        54.1499512279817
                    ],
                    [
                        -2.29482712121554,
                        54.1502364421956
                    ],
                    [
                        -2.29428826094012,
                        54.1510203270924
                    ],
                    [
                        -2.29404503339654,
                        54.1512802524628
                    ],
                    [
                        -2.29203174099338,
                        54.1526364182837
                    ],
                    [
                        -2.29073633212449,
                        54.1536099813687
                    ],
                    [
                        -2.29060467080309,
                        54.153822204312
                    ],
                    [
                        -2.28962364126974,
                        54.1560411829675
                    ],
                    [
                        -2.28930981009921,
                        54.1571400514681
                    ],
                    [
                        -2.28938715792265,
                        54.1584537250363
                    ],
                    [
                        -2.28934986657894,
                        54.1586035994072
                    ],
                    [
                        -2.28922005084515,
                        54.1588966469228
                    ],
                    [
                        -2.28916119552327,
                        54.159116155197
                    ],
                    [
                        -2.28920181454107,
                        54.1591549585282
                    ],
                    [
                        -2.28944906128328,
                        54.1600730999065
                    ],
                    [
                        -2.28940347629729,
                        54.1603068114326
                    ],
                    [
                        -2.28929552246321,
                        54.1605596426242
                    ],
                    [
                        -2.28924643009401,
                        54.1607759305808
                    ],
                    [
                        -2.28926531348449,
                        54.1617588628277
                    ],
                    [
                        -2.28930559158488,
                        54.1621213330173
                    ],
                    [
                        -2.28951512990203,
                        54.1623896152834
                    ],
                    [
                        -2.28958276638227,
                        54.1626005543041
                    ],
                    [
                        -2.28957042479171,
                        54.1630837454611
                    ],
                    [
                        -2.28945601659719,
                        54.1633360646472
                    ],
                    [
                        -2.28941404851735,
                        54.1639940793597
                    ],
                    [
                        -2.28944743454857,
                        54.1641193270864
                    ],
                    [
                        -2.2895767221809,
                        54.1642776970122
                    ],
                    [
                        -2.28961717531274,
                        54.1643713388448
                    ],
                    [
                        -2.28960610122012,
                        54.1644698716387
                    ],
                    [
                        -2.28949436066882,
                        54.1646210979725
                    ],
                    [
                        -2.28949111370287,
                        54.164670005197
                    ],
                    [
                        -2.28960957441755,
                        54.1647467319557
                    ],
                    [
                        -2.28970570677821,
                        54.1647702046609
                    ],
                    [
                        -2.2899447384699,
                        54.1647840804145
                    ],
                    [
                        -2.29001761342746,
                        54.1648006634868
                    ],
                    [
                        -2.29023237058335,
                        54.164880266148
                    ],
                    [
                        -2.29031766582116,
                        54.1649415285642
                    ],
                    [
                        -2.29032223427019,
                        54.1649961706635
                    ],
                    [
                        -2.29040496398266,
                        54.1650949704864
                    ],
                    [
                        -2.29045918135735,
                        54.1652199078833
                    ],
                    [
                        -2.29055728604607,
                        54.1655617277171
                    ],
                    [
                        -2.29061470047583,
                        54.1656208301908
                    ],
                    [
                        -2.29064673280176,
                        54.1656947206808
                    ],
                    [
                        -2.29071700418329,
                        54.1664062672522
                    ],
                    [
                        -2.29082679138254,
                        54.166592674986
                    ],
                    [
                        -2.2909293933925,
                        54.1668376185713
                    ],
                    [
                        -2.29104109169505,
                        54.1672863421859
                    ],
                    [
                        -2.29106789559633,
                        54.1675648777525
                    ],
                    [
                        -2.29118920389209,
                        54.1678809854485
                    ],
                    [
                        -2.29143991727151,
                        54.1682300768613
                    ],
                    [
                        -2.29154783225308,
                        54.1682978785077
                    ],
                    [
                        -2.29179296315748,
                        54.1683966817519
                    ],
                    [
                        -2.29191937514884,
                        54.1684669609493
                    ],
                    [
                        -2.29208481088738,
                        54.1685965679561
                    ],
                    [
                        -2.29225119008373,
                        54.1687870663642
                    ],
                    [
                        -2.29231806930672,
                        54.1689010515414
                    ],
                    [
                        -2.29237192535519,
                        54.1690941940298
                    ],
                    [
                        -2.29237935430036,
                        54.1693124486065
                    ],
                    [
                        -2.29247237009301,
                        54.1695207546046
                    ],
                    [
                        -2.2927284564188,
                        54.1699633581392
                    ],
                    [
                        -2.29279701973229,
                        54.1702083945236
                    ],
                    [
                        -2.29285797254275,
                        54.1704540973768
                    ],
                    [
                        -2.29281392997309,
                        54.1709934843357
                    ],
                    [
                        -2.29268846656442,
                        54.171402897255
                    ],
                    [
                        -2.29256835681502,
                        54.1721466314488
                    ],
                    [
                        -2.29242214861435,
                        54.172455216687
                    ],
                    [
                        -2.29241253308207,
                        54.1725392368611
                    ],
                    [
                        -2.29242895636654,
                        54.172690379673
                    ],
                    [
                        -2.29253824747066,
                        54.1730951663195
                    ],
                    [
                        -2.29272746986507,
                        54.1739959011876
                    ],
                    [
                        -2.29281233799783,
                        54.1750438392997
                    ],
                    [
                        -2.29279216994956,
                        54.1753097021327
                    ],
                    [
                        -2.29282972196516,
                        54.1755257234706
                    ],
                    [
                        -2.29279067544636,
                        54.1760758969899
                    ],
                    [
                        -2.29281650871013,
                        54.1764398373931
                    ],
                    [
                        -2.29294899362258,
                        54.1770464670408
                    ],
                    [
                        -2.29304630917769,
                        54.1776716610594
                    ],
                    [
                        -2.29302554445867,
                        54.177855053695
                    ],
                    [
                        -2.29263407192446,
                        54.1791739122264
                    ],
                    [
                        -2.29254550550193,
                        54.1801706452859
                    ],
                    [
                        -2.29208123921741,
                        54.1808188626116
                    ],
                    [
                        -2.29129546557237,
                        54.1817665964218
                    ],
                    [
                        -2.29107048566494,
                        54.1821952982296
                    ],
                    [
                        -2.29119405494001,
                        54.1830340579957
                    ],
                    [
                        -2.29142503558288,
                        54.183719413016
                    ],
                    [
                        -2.29144400882283,
                        54.1843254736454
                    ],
                    [
                        -2.29147795566787,
                        54.1844461813262
                    ],
                    [
                        -2.29159708417896,
                        54.1846518826033
                    ],
                    [
                        -2.29152439977736,
                        54.184775005616
                    ],
                    [
                        -2.29142562347869,
                        54.1848485816442
                    ],
                    [
                        -2.29140785805361,
                        54.1849370601421
                    ],
                    [
                        -2.29145629532237,
                        54.1850264567617
                    ],
                    [
                        -2.29144586975004,
                        54.1851127605192
                    ],
                    [
                        -2.29138766664529,
                        54.1852034939207
                    ],
                    [
                        -2.29103509617309,
                        54.1855332840604
                    ],
                    [
                        -2.29075399078209,
                        54.1858283890653
                    ],
                    [
                        -2.29011384688517,
                        54.1865827140999
                    ],
                    [
                        -2.28997205673224,
                        54.1868170862736
                    ],
                    [
                        -2.28987058625008,
                        54.1872950978057
                    ],
                    [
                        -2.2897071331919,
                        54.1875877597846
                    ],
                    [
                        -2.28940496258134,
                        54.1880295856027
                    ],
                    [
                        -2.28895497748197,
                        54.1886356947485
                    ],
                    [
                        -2.28880173419413,
                        54.1888118550045
                    ],
                    [
                        -2.28866031984567,
                        54.189102305608
                    ],
                    [
                        -2.28852928364895,
                        54.1892989033475
                    ],
                    [
                        -2.28806437273053,
                        54.1898780827881
                    ],
                    [
                        -2.28800297335923,
                        54.1900319662362
                    ],
                    [
                        -2.28816432228267,
                        54.1900589068063
                    ],
                    [
                        -2.28831838034251,
                        54.1901301865747
                    ],
                    [
                        -2.28840182839053,
                        54.1901508443895
                    ],
                    [
                        -2.28839232531661,
                        54.1901726389875
                    ],
                    [
                        -2.28863894081,
                        54.1902872976187
                    ],
                    [
                        -2.28890753665189,
                        54.1903669602095
                    ],
                    [
                        -2.28949679584544,
                        54.1904254121003
                    ],
                    [
                        -2.28978040107275,
                        54.1904374383902
                    ],
                    [
                        -2.29065317896359,
                        54.1903813759657
                    ],
                    [
                        -2.2911978434447,
                        54.1902805539334
                    ],
                    [
                        -2.29164261354806,
                        54.1902337805841
                    ],
                    [
                        -2.2917795174361,
                        54.1902313537222
                    ],
                    [
                        -2.29240812702054,
                        54.1903276979987
                    ],
                    [
                        -2.29316456011215,
                        54.1903617680302
                    ],
                    [
                        -2.29382147794617,
                        54.1906193316812
                    ],
                    [
                        -2.29411126759321,
                        54.1906474847173
                    ],
                    [
                        -2.29441774413967,
                        54.190654982873
                    ],
                    [
                        -2.29483047490188,
                        54.1906046623431
                    ],
                    [
                        -2.29497159018089,
                        54.1905650741789
                    ],
                    [
                        -2.29498385542146,
                        54.1905442608949
                    ],
                    [
                        -2.29511324373331,
                        54.1905847245565
                    ],
                    [
                        -2.29548809908751,
                        54.1907532275544
                    ],
                    [
                        -2.29612869577883,
                        54.1911245660293
                    ],
                    [
                        -2.29632792607418,
                        54.1912161202426
                    ],
                    [
                        -2.29658101952897,
                        54.1913651241326
                    ],
                    [
                        -2.29701924835358,
                        54.1915566606538
                    ],
                    [
                        -2.29723193220515,
                        54.1917094630011
                    ],
                    [
                        -2.29737399345694,
                        54.1917822131826
                    ],
                    [
                        -2.29764192810854,
                        54.1918489170817
                    ],
                    [
                        -2.29838489079354,
                        54.1918705617965
                    ],
                    [
                        -2.29839493248923,
                        54.191895699636
                    ],
                    [
                        -2.29892119510048,
                        54.1918273766673
                    ],
                    [
                        -2.30077381175745,
                        54.1916642234925
                    ],
                    [
                        -2.30139843254264,
                        54.1916595509464
                    ],
                    [
                        -2.30142794010658,
                        54.1916954928838
                    ],
                    [
                        -2.30164593341467,
                        54.1930158368412
                    ],
                    [
                        -2.30175987376421,
                        54.1933918607211
                    ],
                    [
                        -2.30195839480336,
                        54.1935414251261
                    ],
                    [
                        -2.30210692272302,
                        54.1936082425245
                    ],
                    [
                        -2.30288056643127,
                        54.1937382821023
                    ],
                    [
                        -2.30306408716338,
                        54.1937795850717
                    ],
                    [
                        -2.30323003248337,
                        54.1938414878809
                    ],
                    [
                        -2.30374933924885,
                        54.1941467163098
                    ],
                    [
                        -2.30445264575631,
                        54.1946609871045
                    ],
                    [
                        -2.30456998105869,
                        54.194824105049
                    ],
                    [
                        -2.30463936515952,
                        54.1949838410162
                    ],
                    [
                        -2.30471615797287,
                        54.1957487902329
                    ],
                    [
                        -2.30479643425868,
                        54.1960992878468
                    ],
                    [
                        -2.30486419419567,
                        54.1962318276124
                    ],
                    [
                        -2.30503793575299,
                        54.1964781524445
                    ],
                    [
                        -2.30524884108863,
                        54.1965872450926
                    ],
                    [
                        -2.30542354387069,
                        54.1966470834285
                    ],
                    [
                        -2.30577888440515,
                        54.1969411451838
                    ],
                    [
                        -2.30611764420787,
                        54.1972765178756
                    ],
                    [
                        -2.30618789365896,
                        54.1974590488508
                    ],
                    [
                        -2.30628855998727,
                        54.1982605162532
                    ],
                    [
                        -2.30626972008698,
                        54.198462147255
                    ],
                    [
                        -2.30620625347532,
                        54.1986389313047
                    ],
                    [
                        -2.305997610735,
                        54.1989734301644
                    ],
                    [
                        -2.30581521092744,
                        54.1992086248018
                    ],
                    [
                        -2.30566728175646,
                        54.1993564413041
                    ],
                    [
                        -2.30500883438288,
                        54.199796388747
                    ],
                    [
                        -2.30472406044904,
                        54.2001568538921
                    ],
                    [
                        -2.30461743229951,
                        54.2003315516209
                    ],
                    [
                        -2.30461935855264,
                        54.200547746698
                    ],
                    [
                        -2.304942430792,
                        54.2018575973427
                    ],
                    [
                        -2.30499226000357,
                        54.2022185519742
                    ],
                    [
                        -2.3049996246188,
                        54.2024907754289
                    ],
                    [
                        -2.30494808431355,
                        54.2026043637689
                    ],
                    [
                        -2.30469715575248,
                        54.2029831471182
                    ],
                    [
                        -2.30450891315381,
                        54.203217907708
                    ],
                    [
                        -2.30417649827327,
                        54.2035469391686
                    ],
                    [
                        -2.30406719125781,
                        54.2037620698205
                    ],
                    [
                        -2.30361300081618,
                        54.2043970192285
                    ],
                    [
                        -2.30343257653212,
                        54.2045884889037
                    ],
                    [
                        -2.3033609348399,
                        54.2046994561646
                    ],
                    [
                        -2.30334505123861,
                        54.2048256619472
                    ],
                    [
                        -2.30344402810285,
                        54.2050209773291
                    ],
                    [
                        -2.30347474916174,
                        54.2051408122307
                    ],
                    [
                        -2.30353091090158,
                        54.2058047990549
                    ],
                    [
                        -2.30356792550063,
                        54.2059502588535
                    ],
                    [
                        -2.30354611691399,
                        54.2060169161535
                    ],
                    [
                        -2.30347774459726,
                        54.2060885521123
                    ],
                    [
                        -2.30334237923557,
                        54.2061678280603
                    ],
                    [
                        -2.3032357704959,
                        54.2062733525492
                    ],
                    [
                        -2.3028653178424,
                        54.207026054371
                    ],
                    [
                        -2.30271569519912,
                        54.2072859124947
                    ],
                    [
                        -2.30273285692615,
                        54.2074020087689
                    ],
                    [
                        -2.30291906447915,
                        54.2078237875183
                    ],
                    [
                        -2.30322725992061,
                        54.2084363783283
                    ],
                    [
                        -2.30384068290831,
                        54.208783557786
                    ],
                    [
                        -2.30452100991328,
                        54.209261136084
                    ],
                    [
                        -2.30514215730532,
                        54.2095820913437
                    ],
                    [
                        -2.30594737527591,
                        54.2100722641104
                    ],
                    [
                        -2.3061990069958,
                        54.2103003745748
                    ],
                    [
                        -2.30627984941016,
                        54.2104296490318
                    ],
                    [
                        -2.30627993663053,
                        54.2105632703126
                    ],
                    [
                        -2.30620242104848,
                        54.2107539840962
                    ],
                    [
                        -2.30540327581516,
                        54.2118474807267
                    ],
                    [
                        -2.30512459876435,
                        54.2121457158791
                    ],
                    [
                        -2.30499152598695,
                        54.2123569097212
                    ],
                    [
                        -2.30496286339806,
                        54.2124538834715
                    ],
                    [
                        -2.30496299496514,
                        54.2126134482415
                    ],
                    [
                        -2.30507597735773,
                        54.2131933202697
                    ],
                    [
                        -2.30534300824408,
                        54.213543715975
                    ],
                    [
                        -2.30580284868782,
                        54.2139569216284
                    ],
                    [
                        -2.30684668772398,
                        54.2151994108137
                    ],
                    [
                        -2.30689443804516,
                        54.2152972893013
                    ],
                    [
                        -2.3069137217081,
                        54.2155318392413
                    ],
                    [
                        -2.30677964185074,
                        54.2162147269504
                    ],
                    [
                        -2.30676481706635,
                        54.2166235969768
                    ],
                    [
                        -2.30673202918914,
                        54.2167977519307
                    ],
                    [
                        -2.30592409791035,
                        54.2186193618612
                    ],
                    [
                        -2.3058091129142,
                        54.2190661401783
                    ],
                    [
                        -2.30562397896297,
                        54.2193809158492
                    ],
                    [
                        -2.30553180609494,
                        54.2194013703582
                    ],
                    [
                        -2.30492841999034,
                        54.2194530755724
                    ],
                    [
                        -2.30453894308391,
                        54.2195030773948
                    ],
                    [
                        -2.30410751467859,
                        54.2196014259475
                    ],
                    [
                        -2.30373955959822,
                        54.2197324937116
                    ],
                    [
                        -2.30332131368464,
                        54.2199552118796
                    ],
                    [
                        -2.30298895440792,
                        54.2201842857286
                    ],
                    [
                        -2.30274470175828,
                        54.2203278521729
                    ],
                    [
                        -2.30171087574649,
                        54.220828541606
                    ],
                    [
                        -2.30140961547485,
                        54.2209980489106
                    ],
                    [
                        -2.30119935511521,
                        54.2211329486996
                    ],
                    [
                        -2.30019572605059,
                        54.2218892854667
                    ],
                    [
                        -2.29824306495514,
                        54.2231496041986
                    ],
                    [
                        -2.29459049084002,
                        54.2256307758609
                    ],
                    [
                        -2.29332168624368,
                        54.2265204821739
                    ],
                    [
                        -2.29293507278534,
                        54.2268113802449
                    ],
                    [
                        -2.2915102019017,
                        54.2280454178842
                    ],
                    [
                        -2.29116743026336,
                        54.2282944796674
                    ],
                    [
                        -2.28975459894126,
                        54.2292491514831
                    ],
                    [
                        -2.28871699444002,
                        54.2301357182713
                    ],
                    [
                        -2.28818034915414,
                        54.2304992407234
                    ],
                    [
                        -2.28802758408216,
                        54.2306219878317
                    ],
                    [
                        -2.28691744885352,
                        54.2317780294009
                    ],
                    [
                        -2.28639992495637,
                        54.2323634343293
                    ],
                    [
                        -2.28566842355385,
                        54.2330661794215
                    ],
                    [
                        -2.28495161907158,
                        54.2336790125045
                    ],
                    [
                        -2.28437175181417,
                        54.2341297470422
                    ],
                    [
                        -2.28399056840886,
                        54.234472163002
                    ],
                    [
                        -2.28331930824029,
                        54.2350219678711
                    ],
                    [
                        -2.28237304593877,
                        54.2357431723086
                    ],
                    [
                        -2.28098299245777,
                        54.2366361638356
                    ],
                    [
                        -2.28021948171057,
                        54.2371681919189
                    ],
                    [
                        -2.27754538042746,
                        54.2387831061858
                    ],
                    [
                        -2.27635380150331,
                        54.2395587515627
                    ],
                    [
                        -2.27514641576082,
                        54.2402715103578
                    ],
                    [
                        -2.2747796067893,
                        54.2404880422727
                    ],
                    [
                        -2.272961322973,
                        54.2416425471986
                    ],
                    [
                        -2.27135657912898,
                        54.2426167982178
                    ],
                    [
                        -2.27048565787928,
                        54.243184954903
                    ],
                    [
                        -2.27001179735478,
                        54.2434646233655
                    ],
                    [
                        -2.2693236311306,
                        54.2438256548076
                    ],
                    [
                        -2.26787135282646,
                        54.2446736962557
                    ],
                    [
                        -2.26751905576346,
                        54.2447733393492
                    ],
                    [
                        -2.26719721493489,
                        54.2448369648338
                    ],
                    [
                        -2.26298353220036,
                        54.2458258531593
                    ],
                    [
                        -2.26275050365916,
                        54.2458675208738
                    ],
                    [
                        -2.26276482765504,
                        54.2459267056522
                    ],
                    [
                        -2.2625849630116,
                        54.2464320382282
                    ],
                    [
                        -2.26178170642162,
                        54.248329857146
                    ],
                    [
                        -2.26134465435453,
                        54.2493000183176
                    ],
                    [
                        -2.25993457353759,
                        54.2514526066022
                    ],
                    [
                        -2.25959883210042,
                        54.251869845253
                    ],
                    [
                        -2.25899314494815,
                        54.2523861406602
                    ],
                    [
                        -2.25855706941517,
                        54.2527206399878
                    ],
                    [
                        -2.2579637441927,
                        54.253246705045
                    ],
                    [
                        -2.25722327324217,
                        54.2537772399881
                    ],
                    [
                        -2.25677651020058,
                        54.2542136878461
                    ],
                    [
                        -2.25595113989075,
                        54.2547914656065
                    ],
                    [
                        -2.25576521285658,
                        54.2549844857801
                    ],
                    [
                        -2.25542134068308,
                        54.2554113721389
                    ],
                    [
                        -2.25519160895779,
                        54.2556461338302
                    ],
                    [
                        -2.2549857244505,
                        54.2558356019749
                    ],
                    [
                        -2.25479371128959,
                        54.2559788289906
                    ],
                    [
                        -2.2546130401519,
                        54.2561584281729
                    ],
                    [
                        -2.25448991603165,
                        54.2563574274946
                    ],
                    [
                        -2.25418477647197,
                        54.2574076387496
                    ],
                    [
                        -2.253990235323,
                        54.2578793716232
                    ],
                    [
                        -2.25356168424366,
                        54.258461681686
                    ],
                    [
                        -2.25323926154493,
                        54.2590667850388
                    ],
                    [
                        -2.25302011621873,
                        54.2594215049169
                    ],
                    [
                        -2.25264610930972,
                        54.2598390636375
                    ],
                    [
                        -2.25243741458449,
                        54.2600027856758
                    ],
                    [
                        -2.25227994349344,
                        54.2601570173666
                    ],
                    [
                        -2.25156727234665,
                        54.2605269908232
                    ],
                    [
                        -2.25127350738384,
                        54.2607851437798
                    ],
                    [
                        -2.25056264751418,
                        54.2612489573618
                    ],
                    [
                        -2.25048829540875,
                        54.2613149614086
                    ],
                    [
                        -2.25031724372639,
                        54.2615415388674
                    ],
                    [
                        -2.24994737585144,
                        54.2618823143185
                    ],
                    [
                        -2.24934171745896,
                        54.2623203973198
                    ],
                    [
                        -2.24898755594894,
                        54.2627891798648
                    ],
                    [
                        -2.24872128031597,
                        54.2632173436326
                    ],
                    [
                        -2.24864015047505,
                        54.263398723966
                    ],
                    [
                        -2.24859948222024,
                        54.2635711332455
                    ],
                    [
                        -2.24858937164827,
                        54.2640882791787
                    ],
                    [
                        -2.24818610552464,
                        54.2649007074731
                    ],
                    [
                        -2.24764188498059,
                        54.2657999090952
                    ],
                    [
                        -2.24737731987747,
                        54.2663743769616
                    ],
                    [
                        -2.24672829666918,
                        54.2672687117046
                    ],
                    [
                        -2.24635712760587,
                        54.2677176097497
                    ],
                    [
                        -2.24606719099602,
                        54.2682199951306
                    ],
                    [
                        -2.24585218378141,
                        54.2687198254076
                    ],
                    [
                        -2.2457444245174,
                        54.2690970145289
                    ],
                    [
                        -2.24555139922894,
                        54.2700086441289
                    ],
                    [
                        -2.24540000623059,
                        54.2708000277621
                    ],
                    [
                        -2.24529923443846,
                        54.2714829439234
                    ],
                    [
                        -2.24525616343769,
                        54.2722102676757
                    ],
                    [
                        -2.24521658986618,
                        54.2723419927494
                    ],
                    [
                        -2.24489266266237,
                        54.2730622856375
                    ],
                    [
                        -2.24469248794899,
                        54.2736726616774
                    ],
                    [
                        -2.24432867789778,
                        54.2740813157594
                    ],
                    [
                        -2.2439762922907,
                        54.2745544781072
                    ],
                    [
                        -2.24291881064675,
                        54.2763993842242
                    ],
                    [
                        -2.24262508843823,
                        54.2772139507341
                    ],
                    [
                        -2.2423282881281,
                        54.2777159284091
                    ],
                    [
                        -2.24144779293318,
                        54.2785685403081
                    ],
                    [
                        -2.24127031911529,
                        54.2787732961279
                    ],
                    [
                        -2.24038692422021,
                        54.2793547319475
                    ],
                    [
                        -2.23968258334699,
                        54.2798234929932
                    ],
                    [
                        -2.23837152767089,
                        54.280621707539
                    ],
                    [
                        -2.23833333405281,
                        54.2807800249707
                    ],
                    [
                        -2.23798244389996,
                        54.2813113725619
                    ],
                    [
                        -2.23780707568194,
                        54.2814600767301
                    ],
                    [
                        -2.23749352316589,
                        54.2816326140529
                    ],
                    [
                        -2.23729726907604,
                        54.2818135480473
                    ],
                    [
                        -2.23693038629076,
                        54.281974306124
                    ],
                    [
                        -2.23612312900529,
                        54.2821860390397
                    ],
                    [
                        -2.23594562301025,
                        54.2822769525981
                    ],
                    [
                        -2.23546393551352,
                        54.2827085970856
                    ],
                    [
                        -2.23533762774379,
                        54.2827849025067
                    ],
                    [
                        -2.2350055511831,
                        54.2828778412996
                    ],
                    [
                        -2.2341021255932,
                        54.2830212003676
                    ],
                    [
                        -2.23388847719692,
                        54.2831048907389
                    ],
                    [
                        -2.23356214547663,
                        54.2832944625044
                    ],
                    [
                        -2.23345499656682,
                        54.2833903028521
                    ],
                    [
                        -2.23336424195423,
                        54.2835173561542
                    ],
                    [
                        -2.23324082360416,
                        54.2837902527668
                    ],
                    [
                        -2.23317781630538,
                        54.2841241504665
                    ],
                    [
                        -2.23305196626793,
                        54.2842664373311
                    ],
                    [
                        -2.23292166181983,
                        54.2844709329243
                    ],
                    [
                        -2.23283916506023,
                        54.2853254151861
                    ],
                    [
                        -2.23280823384285,
                        54.2854327009749
                    ],
                    [
                        -2.23238217855497,
                        54.286124243997
                    ],
                    [
                        -2.23230292952058,
                        54.2862129007944
                    ],
                    [
                        -2.23148367471082,
                        54.2867542975129
                    ],
                    [
                        -2.23088367318266,
                        54.287116833507
                    ],
                    [
                        -2.23058408037945,
                        54.2872699630043
                    ],
                    [
                        -2.23031057212825,
                        54.2874842741582
                    ],
                    [
                        -2.22973226239208,
                        54.2881725855359
                    ],
                    [
                        -2.22951518378299,
                        54.2884896830751
                    ],
                    [
                        -2.2293613152518,
                        54.2886520229984
                    ],
                    [
                        -2.22910307709957,
                        54.2888700526084
                    ],
                    [
                        -2.22894982268786,
                        54.2890456118485
                    ],
                    [
                        -2.22858202596544,
                        54.2896553296016
                    ],
                    [
                        -2.2285700421328,
                        54.2897490786185
                    ],
                    [
                        -2.22807755554166,
                        54.2901326617131
                    ],
                    [
                        -2.22780672604485,
                        54.2903011993302
                    ],
                    [
                        -2.22714390854908,
                        54.2905766606322
                    ],
                    [
                        -2.2268384182176,
                        54.2906807174064
                    ],
                    [
                        -2.22643676868584,
                        54.2908581762907
                    ],
                    [
                        -2.2262312388423,
                        54.2909178032923
                    ],
                    [
                        -2.22316846600957,
                        54.2915993325136
                    ],
                    [
                        -2.22257926533721,
                        54.2916966494954
                    ],
                    [
                        -2.22184203934046,
                        54.2918421577422
                    ],
                    [
                        -2.2189146389886,
                        54.2925144508338
                    ],
                    [
                        -2.21760187278108,
                        54.2929477871349
                    ],
                    [
                        -2.21705589433315,
                        54.2931936007594
                    ],
                    [
                        -2.21683474613445,
                        54.2933193952366
                    ],
                    [
                        -2.21677719533324,
                        54.2933691663942
                    ],
                    [
                        -2.216830306316,
                        54.2934655937576
                    ],
                    [
                        -2.21659031910855,
                        54.293533787949
                    ],
                    [
                        -2.21577025598206,
                        54.2938933985018
                    ],
                    [
                        -2.21472732038835,
                        54.2942367748502
                    ],
                    [
                        -2.21049206800871,
                        54.2952418274067
                    ],
                    [
                        -2.2089279962124,
                        54.2958466908302
                    ],
                    [
                        -2.20871326172725,
                        54.295918960469
                    ],
                    [
                        -2.2083142466849,
                        54.2960095229897
                    ],
                    [
                        -2.20812890287095,
                        54.2957749318847
                    ],
                    [
                        -2.20622565901848,
                        54.2961410054937
                    ],
                    [
                        -2.20429418859962,
                        54.2964573368552
                    ],
                    [
                        -2.20407967412514,
                        54.296505855597
                    ],
                    [
                        -2.20398621327109,
                        54.2965705021811
                    ],
                    [
                        -2.20406212183975,
                        54.2967869738015
                    ],
                    [
                        -2.20430508767125,
                        54.2971812891541
                    ],
                    [
                        -2.20467018050327,
                        54.2976831173464
                    ],
                    [
                        -2.20448800362642,
                        54.2977645323147
                    ],
                    [
                        -2.20451309762059,
                        54.2978673925646
                    ],
                    [
                        -2.20446802748679,
                        54.2980741735579
                    ],
                    [
                        -2.2043302322551,
                        54.2981732661216
                    ],
                    [
                        -2.20428449323657,
                        54.2982452409285
                    ],
                    [
                        -2.20405463980767,
                        54.2983714507737
                    ],
                    [
                        -2.20400876674156,
                        54.2984164642525
                    ],
                    [
                        -2.20400907788715,
                        54.2984793737693
                    ],
                    [
                        -2.2041021136777,
                        54.298649971931
                    ],
                    [
                        -2.20408692633679,
                        54.2986859462694
                    ],
                    [
                        -2.20404100850043,
                        54.298721972685
                    ],
                    [
                        -2.20379551997178,
                        54.298794285626
                    ],
                    [
                        -2.20360845195168,
                        54.2988732396523
                    ],
                    [
                        -2.20322656024064,
                        54.2990167804833
                    ],
                    [
                        -2.20303854445828,
                        54.2990581365884
                    ],
                    [
                        -2.20304999489994,
                        54.2990759441861
                    ],
                    [
                        -2.20258995771356,
                        54.2992960953763
                    ],
                    [
                        -2.20174970944561,
                        54.2999752269559
                    ],
                    [
                        -2.20049582063207,
                        54.300226463077
                    ],
                    [
                        -2.20093445091311,
                        54.3007782777628
                    ],
                    [
                        -2.20067911953757,
                        54.3008486792959
                    ],
                    [
                        -2.20060545314909,
                        54.3009520868125
                    ],
                    [
                        -2.20035166267105,
                        54.3010714695128
                    ],
                    [
                        -2.19882279214275,
                        54.3016096986819
                    ],
                    [
                        -2.19868602592913,
                        54.301688418152
                    ],
                    [
                        -2.19852635110791,
                        54.301877648796
                    ],
                    [
                        -2.19803924425474,
                        54.3022856709673
                    ],
                    [
                        -2.19752739024814,
                        54.3028255569226
                    ],
                    [
                        -2.19747360885013,
                        54.3029955704084
                    ],
                    [
                        -2.19759452192655,
                        54.3031991788272
                    ],
                    [
                        -2.19756759452765,
                        54.3033599346554
                    ],
                    [
                        -2.19737629691181,
                        54.3034346574199
                    ],
                    [
                        -2.19737053679467,
                        54.3038275585578
                    ],
                    [
                        -2.19735241898273,
                        54.3038632420353
                    ],
                    [
                        -2.19693582484823,
                        54.3038205270322
                    ],
                    [
                        -2.19673583766792,
                        54.3037759182657
                    ],
                    [
                        -2.19642836678967,
                        54.3037494588422
                    ],
                    [
                        -2.19635157401456,
                        54.3037585712359
                    ],
                    [
                        -2.19606983662256,
                        54.3036498366036
                    ],
                    [
                        -2.19575159736356,
                        54.3036206968487
                    ],
                    [
                        -2.19552750913085,
                        54.3036263453965
                    ],
                    [
                        -2.19529098756805,
                        54.3037063732875
                    ],
                    [
                        -2.19502940688196,
                        54.3036349001611
                    ],
                    [
                        -2.19494249221878,
                        54.3036256044168
                    ],
                    [
                        -2.1945685643332,
                        54.3036715943075
                    ],
                    [
                        -2.19406514632775,
                        54.303758952917
                    ]
                ]
            }
        }
    ]
}